[
  {
    "Código do Item": 10200,
    "Descrição do Item": "EQUIPAMENTO DE INSTRUÇÃO , MODELO DE TREINAMENTO EM TAMANHO NATURAL NOME",
    "Grupo": "69: APARELHOS E ACESSÓRIOS PARA TREINAMENTO",
    "Classe": "6910: ACESSÓRIOS PARA TREINAMENTO",
    "PDM": "09835: EQUIPAMENTO DE INSTRUÇÃO",
    "Status": "Inativo",
    "Sustentável": "Não"
  },
  {
    "Código do Item": 10235,
    "Descrição do Item": "MODELO TAMANHO REDUZIDO , MODELO DE TREINAMENTO EM TAMANHO REDUZID NOME",
    "Grupo": "69: APARELHOS E ACESSÓRIOS PARA TREINAMENTO",
    "Classe": "6910: ACESSÓRIOS PARA TREINAMENTO",
    "PDM": "09836: MODELO TAMANHO REDUZIDO",
    "Status": "Ativo",
    "Sustentável": "Não"
  },
  {
    "Código do Item": 10278,
    "Descrição do Item": "MOTOR SECCIONADO DE TREINAMENTO , MOTOR SECCIONADO DE TREINAMENTO NOME",
    "Grupo": "69: APARELHOS E ACESSÓRIOS PARA TREINAMENTO",
    "Classe": "6910: ACESSÓRIOS PARA TREINAMENTO",
    "PDM": "09993: MOTOR SECCIONADO DE TREINAMENTO",
    "Status": "Ativo",
    "Sustentável": "Não"
  },
  {
    "Código do Item": 10308,
    "Descrição do Item": "MUNICAO SECCIONADA , MUNICAO SECCIONADA NOME",
    "Grupo": "69: APARELHOS E ACESSÓRIOS PARA TREINAMENTO",
    "Classe": "6920: ACESSÓRIOS PARA TREINAMENTO DE ARMAMENTO",
    "PDM": "10022: MUNICAO SECCIONADA",
    "Status": "Ativo",
    "Sustentável": "Não"
  },
  {
    "Código do Item": 10316,
    "Descrição do Item": "PLANTA PARA TREINAMENTO , PLANTA PARA TREINAMENTO NOME",
    "Grupo": "69: APARELHOS E ACESSÓRIOS PARA TREINAMENTO",
    "Classe": "6910: ACESSÓRIOS PARA TREINAMENTO",
    "PDM": "10883: PLANTA PARA TREINAMENTO",
    "Status": "Ativo",
    "Sustentável": "Não"
  },
  {
    "Código do Item": 10332,
    "Descrição do Item": "MAPA PARA TREINAMENTO , MAPA PARA TREINAMENTO NOME",
    "Grupo": "69: APARELHOS E ACESSÓRIOS PARA TREINAMENTO",
    "Classe": "6910: ACESSÓRIOS PARA TREINAMENTO",
    "PDM": "09137: MAPA PARA TREINAMENTO",
    "Status": "Ativo",
    "Sustentável": "Não"
  },
  {
    "Código do Item": 10359,
    "Descrição do Item": "FILME EDUCACIONAL , FILME EDUCACIONAL NOME",
    "Grupo": "69: APARELHOS E ACESSÓRIOS PARA TREINAMENTO",
    "Classe": "6910: ACESSÓRIOS PARA TREINAMENTO",
    "PDM": "07439: FILME EDUCACIONAL",
    "Status": "Ativo",
    "Sustentável": "Não"
  },
  {
    "Código do Item": 10391,
    "Descrição do Item": "FILME PARA TREINAMENTO , FILME PARA TREINAMENTO NOME",
    "Grupo": "69: APARELHOS E ACESSÓRIOS PARA TREINAMENTO",
    "Classe": "6910: ACESSÓRIOS PARA TREINAMENTO",
    "PDM": "07445: FILME PARA TREINAMENTO",
    "Status": "Ativo",
    "Sustentável": "Não"
  },
  {
    "Código do Item": 10588,
    "Descrição do Item": "APARELHO NAVEGAÇÃO PARA TREINAMENTO , APARELHO DE NAVEGACAO PARA TREINAMENTO NOME",
    "Grupo": "69: APARELHOS E ACESSÓRIOS PARA TREINAMENTO",
    "Classe": "6930: ACESSÓRIOS PARA TREINAMENTO OPERACIONAL",
    "PDM": "02725: APARELHO NAVEGAÇÃO PARA TREINAMENTO",
    "Status": "Ativo",
    "Sustentável": "Não"
  },
  {
    "Código do Item": 10596,
    "Descrição do Item": "APARELHO COMUNICAÇÃO PARA TREINAMENTO , APARELHO DE COMUNICACAO PARA TREINAMENTO NOME",
    "Grupo": "69: APARELHOS E ACESSÓRIOS PARA TREINAMENTO",
    "Classe": "6930: ACESSÓRIOS PARA TREINAMENTO OPERACIONAL",
    "PDM": "02682: APARELHO COMUNICAÇÃO PARA TREINAMENTO",
    "Status": "Ativo",
    "Sustentável": "Não"
  },
  {
    "Código do Item": 10600,
    "Descrição do Item": "APARELHO DE RADAR PARA TREINAMENTO , APARELHO DE RADAR PARA TREINAMENTO NOME",
    "Grupo": "69: APARELHOS E ACESSÓRIOS PARA TREINAMENTO",
    "Classe": "6930: ACESSÓRIOS PARA TREINAMENTO OPERACIONAL",
    "PDM": "02733: APARELHO DE RADAR PARA TREINAMENTO",
    "Status": "Ativo",
    "Sustentável": "Não"
  },
  {
    "Código do Item": 10618,
    "Descrição do Item": "PLACA DE TREINAMENTO EM CIRCUITO , PLACA DE TREINAMENTO EM CIRCUITO NOME",
    "Grupo": "69: APARELHOS E ACESSÓRIOS PARA TREINAMENTO",
    "Classe": "6940: ACESSÓRIOS PARA TREINAMENTO DE COMUNICAÇÕES",
    "PDM": "10843: PLACA DE TREINAMENTO EM CIRCUITO",
    "Status": "Ativo",
    "Sustentável": "Não"
  },
  {
    "Código do Item": 10626,
    "Descrição do Item": "SIMULADOR , SIMULADOR DE DETECTOR DE RADIO - FREQUEN NOME",
    "Grupo": "69: APARELHOS E ACESSÓRIOS PARA TREINAMENTO",
    "Classe": "6940: ACESSÓRIOS PARA TREINAMENTO DE COMUNICAÇÕES",
    "PDM": "12071: SIMULADOR",
    "Status": "Inativo",
    "Sustentável": "Não"
  },
  {
    "Código do Item": 10634,
    "Descrição do Item": "TREINAMENTO EM RADAR , TREINAMENTO EM RADAR NOME",
    "Grupo": "69: APARELHOS E ACESSÓRIOS PARA TREINAMENTO",
    "Classe": "6940: ACESSÓRIOS PARA TREINAMENTO DE COMUNICAÇÕES",
    "PDM": "12953: TREINAMENTO EM RADAR",
    "Status": "Ativo",
    "Sustentável": "Não"
  },
  {
    "Código do Item": 10642,
    "Descrição do Item": "KIT ELETRÔNICO , KIT ELETRONICO NOME",
    "Grupo": "69: APARELHOS E ACESSÓRIOS PARA TREINAMENTO",
    "Classe": "6940: ACESSÓRIOS PARA TREINAMENTO DE COMUNICAÇÕES",
    "PDM": "08579: KIT ELETRÔNICO",
    "Status": "Ativo",
    "Sustentável": "Não"
  },
  {
    "Código do Item": 10669,
    "Descrição do Item": "SIMULADOR DE POSICAO DE ANTENA , SIMULADOR DE POSICAO DE ANTENA NOME",
    "Grupo": "69: APARELHOS E ACESSÓRIOS PARA TREINAMENTO",
    "Classe": "6940: ACESSÓRIOS PARA TREINAMENTO DE COMUNICAÇÕES",
    "PDM": "12072: SIMULADOR DE POSICAO DE ANTENA",
    "Status": "Ativo",
    "Sustentável": "Não"
  },
  {
    "Código do Item": 10685,
    "Descrição do Item": "PRATICA EM CODIGO TELEGRAFICO , PRATICA EM CODIGO TELEGRAFICO NOME",
    "Grupo": "69: APARELHOS E ACESSÓRIOS PARA TREINAMENTO",
    "Classe": "6940: ACESSÓRIOS PARA TREINAMENTO DE COMUNICAÇÕES",
    "PDM": "11141: PRATICA EM CODIGO TELEGRAFICO",
    "Status": "Ativo",
    "Sustentável": "Não"
  },
  {
    "Código do Item": 46132,
    "Descrição do Item": "GERADORES DE FUMAÇA , GERADORES DE FUMACA NOME",
    "Grupo": "69: APARELHOS E ACESSÓRIOS PARA TREINAMENTO",
    "Classe": "6910: ACESSÓRIOS PARA TREINAMENTO",
    "PDM": "07986: GERADORES DE FUMAÇA",
    "Status": "Ativo",
    "Sustentável": "Não"
  },
  {
    "Código do Item": 53686,
    "Descrição do Item": "PELICULA CINEMATOGRAFICA PARA TREINAMENTO , PELICULA CINEMATOGRAFICA PARA TREINAMENT NOME",
    "Grupo": "69: APARELHOS E ACESSÓRIOS PARA TREINAMENTO",
    "Classe": "6910: ACESSÓRIOS PARA TREINAMENTO",
    "PDM": "10597: PELICULA CINEMATOGRAFICA PARA TREINAMENTO",
    "Status": "Inativo",
    "Sustentável": "Não"
  },
  {
    "Código do Item": 53694,
    "Descrição do Item": "PELICULA FOTOGRAFICA , PELICULA FOTOGRAFICA PARA TREINAMENTO NOME",
    "Grupo": "69: APARELHOS E ACESSÓRIOS PARA TREINAMENTO",
    "Classe": "6910: ACESSÓRIOS PARA TREINAMENTO",
    "PDM": "10601: PELICULA FOTOGRAFICA",
    "Status": "Ativo",
    "Sustentável": "Não"
  },
  {
    "Código do Item": 53708,
    "Descrição do Item": "EQUIPAMENTO DE TREINAMENTO DE NAVEGACAO , EQUIPAMENTO DE TREINAMENTO DE NAVEGACAO NOME",
    "Grupo": "69: APARELHOS E ACESSÓRIOS PARA TREINAMENTO",
    "Classe": "6910: ACESSÓRIOS PARA TREINAMENTO",
    "PDM": "06769: EQUIPAMENTO DE TREINAMENTO DE NAVEGACAO",
    "Status": "Ativo",
    "Sustentável": "Não"
  },
  {
    "Código do Item": 53716,
    "Descrição do Item": "EQUIPAMENTO DE TREINAMENTO DE INSTRUMENTO DE VOO , EQUIPAMENTO DE TREINAMENTO DE INSTRUMENT NOME",
    "Grupo": "69: APARELHOS E ACESSÓRIOS PARA TREINAMENTO",
    "Classe": "6910: ACESSÓRIOS PARA TREINAMENTO",
    "PDM": "06768: EQUIPAMENTO DE TREINAMENTO DE INSTRUMENTO DE VOO",
    "Status": "Inativo",
    "Sustentável": "Não"
  },
  {
    "Código do Item": 53724,
    "Descrição do Item": "EQUIPAMENTO PARA TREINAMENTO DE VEICULO , EQUIPAMENTO PARA TREINAMENTO DE VEICULO NOME",
    "Grupo": "69: APARELHOS E ACESSÓRIOS PARA TREINAMENTO",
    "Classe": "6910: ACESSÓRIOS PARA TREINAMENTO",
    "PDM": "06839: EQUIPAMENTO PARA TREINAMENTO DE VEICULO",
    "Status": "Ativo",
    "Sustentável": "Não"
  },
  {
    "Código do Item": 53732,
    "Descrição do Item": "EQUIPAMENTO DE TREINAMENTO - INSTRUMENTO DE AERONAVE , EQUIPAMENTO DE TREINAMENTO - INSTRUMENTO NOME",
    "Grupo": "69: APARELHOS E ACESSÓRIOS PARA TREINAMENTO",
    "Classe": "6910: ACESSÓRIOS PARA TREINAMENTO",
    "PDM": "06767: EQUIPAMENTO DE TREINAMENTO - INSTRUMENTO DE AERONAVE",
    "Status": "Ativo",
    "Sustentável": "Não"
  },
  {
    "Código do Item": 53740,
    "Descrição do Item": "EQUIPAMENTO DE TREINAMENTO EM MOTOR , EQUIPAMENTO DE TREINAMENTO EM MOTOR NOME",
    "Grupo": "69: APARELHOS E ACESSÓRIOS PARA TREINAMENTO",
    "Classe": "6910: ACESSÓRIOS PARA TREINAMENTO",
    "PDM": "06771: EQUIPAMENTO DE TREINAMENTO EM MOTOR",
    "Status": "Ativo",
    "Sustentável": "Não"
  },
  {
    "Código do Item": 53759,
    "Descrição do Item": "EQUIPAMENTO DE TREINAMENTO DE SISTEMA HIDRAULICO , EQUIPAMENTO DE TREINAMENTO DE SISTEMA HI NOME",
    "Grupo": "69: APARELHOS E ACESSÓRIOS PARA TREINAMENTO",
    "Classe": "6910: ACESSÓRIOS PARA TREINAMENTO",
    "PDM": "06770: EQUIPAMENTO DE TREINAMENTO DE SISTEMA HIDRAULICO",
    "Status": "Ativo",
    "Sustentável": "Não"
  },
  {
    "Código do Item": 53767,
    "Descrição do Item": "APARELHO DE TREINAR BOMBARDEIO , APARELHO DE TREINAR BOMBARDEIO NOME",
    "Grupo": "69: APARELHOS E ACESSÓRIOS PARA TREINAMENTO",
    "Classe": "6920: ACESSÓRIOS PARA TREINAMENTO DE ARMAMENTO",
    "PDM": "02748: APARELHO DE TREINAR BOMBARDEIO",
    "Status": "Ativo",
    "Sustentável": "Não"
  },
  {
    "Código do Item": 53775,
    "Descrição do Item": "APARELHO DE TREINAR TIRO DE CANHAO , APARELHO DE TREINAR TIRO DE CANHAO NOME",
    "Grupo": "69: APARELHOS E ACESSÓRIOS PARA TREINAMENTO",
    "Classe": "6920: ACESSÓRIOS PARA TREINAMENTO DE ARMAMENTO",
    "PDM": "02750: APARELHO DE TREINAR TIRO DE CANHAO",
    "Status": "Ativo",
    "Sustentável": "Não"
  },
  {
    "Código do Item": 53783,
    "Descrição do Item": "CONJUNTO DE TREINAMENTO DE MISSIL GUIADO , CONJUNTO DE TREINAMENTO DE MISSIL GUIADO NOME",
    "Grupo": "69: APARELHOS E ACESSÓRIOS PARA TREINAMENTO",
    "Classe": "6920: ACESSÓRIOS PARA TREINAMENTO DE ARMAMENTO",
    "PDM": "05742: CONJUNTO DE TREINAMENTO DE MISSIL GUIADO",
    "Status": "Ativo",
    "Sustentável": "Não"
  },
  {
    "Código do Item": 53791,
    "Descrição do Item": "BASE ALVO DE TIRO , ALVO REBOCADO PARA TREINAMENTO DE TIRO NOME",
    "Grupo": "69: APARELHOS E ACESSÓRIOS PARA TREINAMENTO",
    "Classe": "6920: ACESSÓRIOS PARA TREINAMENTO DE ARMAMENTO",
    "PDM": "02383: BASE ALVO DE TIRO",
    "Status": "Inativo",
    "Sustentável": "Não"
  },
  {
    "Código do Item": 53805,
    "Descrição do Item": "ALVO DE TIRO , ALVO DE TIRO DE CANHAO NOME",
    "Grupo": "69: APARELHOS E ACESSÓRIOS PARA TREINAMENTO",
    "Classe": "6920: ACESSÓRIOS PARA TREINAMENTO DE ARMAMENTO",
    "PDM": "02382: ALVO DE TIRO",
    "Status": "Inativo",
    "Sustentável": "Não"
  },
  {
    "Código do Item": 53813,
    "Descrição do Item": "TREINADOR DE VOO SIMULADO ( LINK TRAINER ) , TREINADOR DE VOO SIMULADO ( LINK TRAINER NOME",
    "Grupo": "69: APARELHOS E ACESSÓRIOS PARA TREINAMENTO",
    "Classe": "6930: ACESSÓRIOS PARA TREINAMENTO OPERACIONAL",
    "PDM": "12950: TREINADOR DE VOO SIMULADO ( LINK TRAINER )",
    "Status": "Ativo",
    "Sustentável": "Não"
  },
  {
    "Código do Item": 53821,
    "Descrição do Item": "DISPOSITIVO TREINAMENTO DE PILOTO AUTOMÁTICO , DISPOSITIVO DE TREINAMENTO DE PILOTO AUT NOME",
    "Grupo": "69: APARELHOS E ACESSÓRIOS PARA TREINAMENTO",
    "Classe": "6930: ACESSÓRIOS PARA TREINAMENTO OPERACIONAL",
    "PDM": "06318: DISPOSITIVO TREINAMENTO DE PILOTO AUTOMÁTICO",
    "Status": "Ativo",
    "Sustentável": "Não"
  },
  {
    "Código do Item": 53830,
    "Descrição do Item": "DISPOSITIVO DE TREINAMENTO DE DERIVOMETRO , DISPOSITIVO DE TREINAMENTO DE DERIVOMETR NOME",
    "Grupo": "69: APARELHOS E ACESSÓRIOS PARA TREINAMENTO",
    "Classe": "6930: ACESSÓRIOS PARA TREINAMENTO OPERACIONAL",
    "PDM": "06316: DISPOSITIVO DE TREINAMENTO DE DERIVOMETRO",
    "Status": "Ativo",
    "Sustentável": "Não"
  },
  {
    "Código do Item": 53848,
    "Descrição do Item": "DISPOSITIVO DE TREINAMENTO DE NAVEGACAO CELESTIAL , DISPOSITIVO DE TREINAMENTO DE NAVEGACAO NOME",
    "Grupo": "69: APARELHOS E ACESSÓRIOS PARA TREINAMENTO",
    "Classe": "6930: ACESSÓRIOS PARA TREINAMENTO OPERACIONAL",
    "PDM": "06317: DISPOSITIVO DE TREINAMENTO DE NAVEGACAO CELESTIAL",
    "Status": "Ativo",
    "Sustentável": "Não"
  },
  {
    "Código do Item": 53856,
    "Descrição do Item": "APARELHO DE TREINAR PILOTAGEM , APARELHO DE TREINAR PILOTAGEM NOME",
    "Grupo": "69: APARELHOS E ACESSÓRIOS PARA TREINAMENTO",
    "Classe": "6930: ACESSÓRIOS PARA TREINAMENTO OPERACIONAL",
    "PDM": "02749: APARELHO DE TREINAR PILOTAGEM",
    "Status": "Ativo",
    "Sustentável": "Não"
  },
  {
    "Código do Item": 53864,
    "Descrição do Item": "APARELHO DE TREINAR ATERRISSAGEM , APARELHO DE TREINAR ATERRISSAGEM NOME",
    "Grupo": "69: APARELHOS E ACESSÓRIOS PARA TREINAMENTO",
    "Classe": "6930: ACESSÓRIOS PARA TREINAMENTO OPERACIONAL",
    "PDM": "02747: APARELHO DE TREINAR ATERRISSAGEM",
    "Status": "Ativo",
    "Sustentável": "Não"
  },
  {
    "Código do Item": 53880,
    "Descrição do Item": "TREINADOR PARA RADAR DE NAVEGACAO , TREINADOR PARA RADAR DE NAVEGACAO NOME",
    "Grupo": "69: APARELHOS E ACESSÓRIOS PARA TREINAMENTO",
    "Classe": "6940: ACESSÓRIOS PARA TREINAMENTO DE COMUNICAÇÕES",
    "PDM": "12952: TREINADOR PARA RADAR DE NAVEGACAO",
    "Status": "Ativo",
    "Sustentável": "Não"
  },
  {
    "Código do Item": 53899,
    "Descrição do Item": "TREINADOR DE RADAR SUPERSONICO , TREINADOR DE RADAR SUPERSONICO NOME",
    "Grupo": "69: APARELHOS E ACESSÓRIOS PARA TREINAMENTO",
    "Classe": "6940: ACESSÓRIOS PARA TREINAMENTO DE COMUNICAÇÕES",
    "PDM": "12949: TREINADOR DE RADAR SUPERSONICO",
    "Status": "Ativo",
    "Sustentável": "Não"
  },
  {
    "Código do Item": 53902,
    "Descrição do Item": "TREINADOR DE RADAR DE BUSCA , TREINADOR DE RADAR DE BUSCA NOME",
    "Grupo": "69: APARELHOS E ACESSÓRIOS PARA TREINAMENTO",
    "Classe": "6940: ACESSÓRIOS PARA TREINAMENTO DE COMUNICAÇÕES",
    "PDM": "12948: TREINADOR DE RADAR DE BUSCA",
    "Status": "Ativo",
    "Sustentável": "Não"
  },
  {
    "Código do Item": 53910,
    "Descrição do Item": "TREINADOR PARA RADAR DE DETECCAO , TREINADOR PARA RADAR DE DETECCAO NOME",
    "Grupo": "69: APARELHOS E ACESSÓRIOS PARA TREINAMENTO",
    "Classe": "6940: ACESSÓRIOS PARA TREINAMENTO DE COMUNICAÇÕES",
    "PDM": "12951: TREINADOR PARA RADAR DE DETECCAO",
    "Status": "Ativo",
    "Sustentável": "Não"
  },
  {
    "Código do Item": 53929,
    "Descrição do Item": "EQUIPAMENTO DE PRATICA DE CODIGO DE COMUNICACAO , EQUIPAMENTO DE PRATICA DE CODIGO DE COMU NOME",
    "Grupo": "69: APARELHOS E ACESSÓRIOS PARA TREINAMENTO",
    "Classe": "6940: ACESSÓRIOS PARA TREINAMENTO DE COMUNICAÇÕES",
    "PDM": "06725: EQUIPAMENTO DE PRATICA DE CODIGO DE COMUNICACAO",
    "Status": "Ativo",
    "Sustentável": "Não"
  },
  {
    "Código do Item": 59455,
    "Descrição do Item": "APARELHO INSTRUÇÃO DE COMUNICAÇÃO , APARELHO DE INSTRUCAO DE COMUNICACAO NOME",
    "Grupo": "69: APARELHOS E ACESSÓRIOS PARA TREINAMENTO",
    "Classe": "6940: ACESSÓRIOS PARA TREINAMENTO DE COMUNICAÇÕES",
    "PDM": "02714: APARELHO INSTRUÇÃO DE COMUNICAÇÃO",
    "Status": "Ativo",
    "Sustentável": "Não"
  },
  {
    "Código do Item": 59463,
    "Descrição do Item": "APARELHO DE INSTRUCAO DE RADAR , APARELHO DE INSTRUCAO DE RADAR NOME",
    "Grupo": "69: APARELHOS E ACESSÓRIOS PARA TREINAMENTO",
    "Classe": "6940: ACESSÓRIOS PARA TREINAMENTO DE COMUNICAÇÕES",
    "PDM": "02715: APARELHO DE INSTRUCAO DE RADAR",
    "Status": "Ativo",
    "Sustentável": "Não"
  },
  {
    "Código do Item": 97322,
    "Descrição do Item": "EQUIPAMENTOS/ACESSÓRIOS SIMULAÇÃO ACIDENTES , ESQUELETO HUMANO - ( PARA FINS DIDATICOS NOME",
    "Grupo": "69: APARELHOS E ACESSÓRIOS PARA TREINAMENTO",
    "Classe": "6910: ACESSÓRIOS PARA TREINAMENTO",
    "PDM": "07058: EQUIPAMENTOS/ACESSÓRIOS SIMULAÇÃO ACIDENTES",
    "Status": "Inativo",
    "Sustentável": "Não"
  },
  {
    "Código do Item": 97330,
    "Descrição do Item": "MODELO ANATÔMICO PARA FINS DIDÁTICOS , MODELOS ANATOMICOS PARA FINS DIDATICOS NOME",
    "Grupo": "69: APARELHOS E ACESSÓRIOS PARA TREINAMENTO",
    "Classe": "6910: ACESSÓRIOS PARA TREINAMENTO",
    "PDM": "09837: MODELO ANATÔMICO PARA FINS DIDÁTICOS",
    "Status": "Ativo",
    "Sustentável": "Não"
  },
  {
    "Código do Item": 111139,
    "Descrição do Item": "MATERIAL DIDATICO - ESQUELETO / SIMULADOR MEDICO / , MATERIAL DIDATICO - ESQUELETO / SIMULADO NOME",
    "Grupo": "69: APARELHOS E ACESSÓRIOS PARA TREINAMENTO",
    "Classe": "6910: ACESSÓRIOS PARA TREINAMENTO",
    "PDM": "09458: MATERIAL DIDATICO - ESQUELETO / SIMULADOR MEDICO /",
    "Status": "Ativo",
    "Sustentável": "Não"
  },
  {
    "Código do Item": 113034,
    "Descrição do Item": "PROGRAMA / PRODUCAO - EDUCATIVO, INSTITUCIONAL , PROGRAMA / PRODUCAO - EDUCATIVO, INSTITU NOME",
    "Grupo": "69: APARELHOS E ACESSÓRIOS PARA TREINAMENTO",
    "Classe": "6910: ACESSÓRIOS PARA TREINAMENTO",
    "PDM": "11252: PROGRAMA / PRODUCAO - EDUCATIVO, INSTITUCIONAL",
    "Status": "Ativo",
    "Sustentável": "Não"
  },
  {
    "Código do Item": 150093,
    "Descrição do Item": "MODELO PARA ESTUDO , MODELO PARA ESTUDO NOME",
    "Grupo": "69: APARELHOS E ACESSÓRIOS PARA TREINAMENTO",
    "Classe": "6910: ACESSÓRIOS PARA TREINAMENTO",
    "PDM": "16607: MODELO PARA ESTUDO",
    "Status": "Ativo",
    "Sustentável": "Não"
  },
  {
    "Código do Item": 150154,
    "Descrição do Item": "REGLETE - DEFICIENTE VISUAL , REGLETE - DEFICIENTE VISUAL NOME",
    "Grupo": "69: APARELHOS E ACESSÓRIOS PARA TREINAMENTO",
    "Classe": "6910: ACESSÓRIOS PARA TREINAMENTO",
    "PDM": "16576: REGLETE - DEFICIENTE VISUAL",
    "Status": "Ativo",
    "Sustentável": "Não"
  },
  {
    "Código do Item": 150187,
    "Descrição do Item": "EQUIPAMENTOS/ACESSÓRIOS SIMULAÇÃO ACIDENTES , EQUIPAMENTOS/ACESSÓRIOS SIMULAÇÃO ACIDEN NOME",
    "Grupo": "69: APARELHOS E ACESSÓRIOS PARA TREINAMENTO",
    "Classe": "6910: ACESSÓRIOS PARA TREINAMENTO",
    "PDM": "07058: EQUIPAMENTOS/ACESSÓRIOS SIMULAÇÃO ACIDENTES",
    "Status": "Ativo",
    "Sustentável": "Não"
  },
  {
    "Código do Item": 150237,
    "Descrição do Item": "CONJUNTO INSTRUÇÃO , CONJUNTO INSTRUÇÃO NOME",
    "Grupo": "69: APARELHOS E ACESSÓRIOS PARA TREINAMENTO",
    "Classe": "6910: ACESSÓRIOS PARA TREINAMENTO",
    "PDM": "13720: CONJUNTO INSTRUÇÃO",
    "Status": "Ativo",
    "Sustentável": "Não"
  },
  {
    "Código do Item": 150317,
    "Descrição do Item": "SIMULADOR , SIMULADOR NOME",
    "Grupo": "69: APARELHOS E ACESSÓRIOS PARA TREINAMENTO",
    "Classe": "6940: ACESSÓRIOS PARA TREINAMENTO DE COMUNICAÇÕES",
    "PDM": "12071: SIMULADOR",
    "Status": "Ativo",
    "Sustentável": "Não"
  },
  {
    "Código do Item": 150884,
    "Descrição do Item": "ALVO DE TIRO , ALVO DE TIRO NOME",
    "Grupo": "69: APARELHOS E ACESSÓRIOS PARA TREINAMENTO",
    "Classe": "6920: ACESSÓRIOS PARA TREINAMENTO DE ARMAMENTO",
    "PDM": "02382: ALVO DE TIRO",
    "Status": "Ativo",
    "Sustentável": "Não"
  },
  {
    "Código do Item": 150893,
    "Descrição do Item": "EQUIPAMENTO ALVO MÓVEL , EQUIPAMENTO ALVO MÓVEL NOME",
    "Grupo": "69: APARELHOS E ACESSÓRIOS PARA TREINAMENTO",
    "Classe": "6920: ACESSÓRIOS PARA TREINAMENTO DE ARMAMENTO",
    "PDM": "14299: EQUIPAMENTO ALVO MÓVEL",
    "Status": "Ativo",
    "Sustentável": "Não"
  },
  {
    "Código do Item": 196910,
    "Descrição do Item": "ACESSÓRIOS PARA ESTUDO/TREINAMENTO , ACESSÓRIOS PARA TREINAMENTO NOME",
    "Grupo": "69: APARELHOS E ACESSÓRIOS PARA TREINAMENTO",
    "Classe": "6910: ACESSÓRIOS PARA TREINAMENTO",
    "PDM": "17181: ACESSÓRIOS PARA ESTUDO/TREINAMENTO",
    "Status": "Ativo",
    "Sustentável": "Não"
  },
  {
    "Código do Item": 196920,
    "Descrição do Item": "ACESSÓRIOS PARA TREINAMENTO DE ARMAMENTO , ACESSÓRIOS PARA TREINAMENTO DE ARMAMENTO NOME",
    "Grupo": "69: APARELHOS E ACESSÓRIOS PARA TREINAMENTO",
    "Classe": "6920: ACESSÓRIOS PARA TREINAMENTO DE ARMAMENTO",
    "PDM": "17182: ACESSÓRIOS PARA TREINAMENTO DE ARMAMENTO",
    "Status": "Ativo",
    "Sustentável": "Não"
  },
  {
    "Código do Item": 196930,
    "Descrição do Item": "ACESSÓRIOS PARA TREINAMENTO OPERACIONAL , ACESSÓRIOS PARA TREINAMENTO OPERACIONAL NOME",
    "Grupo": "69: APARELHOS E ACESSÓRIOS PARA TREINAMENTO",
    "Classe": "6930: ACESSÓRIOS PARA TREINAMENTO OPERACIONAL",
    "PDM": "17183: ACESSÓRIOS PARA TREINAMENTO OPERACIONAL",
    "Status": "Inativo",
    "Sustentável": "Não"
  },
  {
    "Código do Item": 196940,
    "Descrição do Item": "ACESSÓRIOS PARA TREINAMENTO DE COMUNICAÇÕES , ACESSÓRIOS PARA TREINAMENTO DE COMUNICAÇ NOME",
    "Grupo": "69: APARELHOS E ACESSÓRIOS PARA TREINAMENTO",
    "Classe": "6940: ACESSÓRIOS PARA TREINAMENTO DE COMUNICAÇÕES",
    "PDM": "17184: ACESSÓRIOS PARA TREINAMENTO DE COMUNICAÇÕES",
    "Status": "Inativo",
    "Sustentável": "Não"
  },
  {
    "Código do Item": 226393,
    "Descrição do Item": "CONJUNTO INSTRUÇÃO , TIPO MATERIAL DIDÁTICO, COMPONENTES FICHA/SUPORTE/LUPA/LEVANTADOR E FICHÁRIO, FINALIDADE INSTRUÇÃO E FORMAÇÃO PROFISSIONAL",
    "Grupo": "69: APARELHOS E ACESSÓRIOS PARA TREINAMENTO",
    "Classe": "6910: ACESSÓRIOS PARA TREINAMENTO",
    "PDM": "13720: CONJUNTO INSTRUÇÃO",
    "Status": "Ativo",
    "Sustentável": "Não"
  },
  {
    "Código do Item": 231258,
    "Descrição do Item": "EQUIPAMENTO ALVO MÓVEL , MATERIAL ESTRUTURA BASE FERRO, ACABAMENTO ESTRUTURA GALVANIZADO E PINTADO, COMPRIMENTO ESTRUTURA 20 M, ALTURA ESTRUTURA 2,80 M, POTÊNCIA MOTOR ACIONAMENTO 1/2 CV, TENSÃO ALIMENTAÇÃO 220 V, QUANTIDADE ALVOS 5, TIPO COMANDO CHAVE REVERSORA",
    "Grupo": "69: APARELHOS E ACESSÓRIOS PARA TREINAMENTO",
    "Classe": "6920: ACESSÓRIOS PARA TREINAMENTO DE ARMAMENTO",
    "PDM": "14299: EQUIPAMENTO ALVO MÓVEL",
    "Status": "Ativo",
    "Sustentável": "Não"
  },
  {
    "Código do Item": 237401,
    "Descrição do Item": "ALVO DE TIRO , MATERIAL CHAPA METÁLICA DE 5/16 POL, TIPO DISCO, TAMANHO 0,20 X 0,50 X 1 M",
    "Grupo": "69: APARELHOS E ACESSÓRIOS PARA TREINAMENTO",
    "Classe": "6920: ACESSÓRIOS PARA TREINAMENTO DE ARMAMENTO",
    "PDM": "02382: ALVO DE TIRO",
    "Status": "Ativo",
    "Sustentável": "Não"
  },
  {
    "Código do Item": 237402,
    "Descrição do Item": "ALVO DE TIRO , MATERIAL CHAPA METÁLICA DE 5/16 POL, TIPO SILHUETA, TAMANHO 1 X 0,80 M",
    "Grupo": "69: APARELHOS E ACESSÓRIOS PARA TREINAMENTO",
    "Classe": "6920: ACESSÓRIOS PARA TREINAMENTO DE ARMAMENTO",
    "PDM": "02382: ALVO DE TIRO",
    "Status": "Ativo",
    "Sustentável": "Não"
  },
  {
    "Código do Item": 250677,
    "Descrição do Item": "OBRÉIA , MATERIAL PAPEL CELULOSE VEGETAL, FORMATO CIRCULAR, APRESENTAÇÃO AUTO ADESIVA, COR BRANCA, TAMANHO PADRÃO, APLICAÇÃO COBRIR FUROS CAUSADOS POR PROJÉTEIS NOS ALVOS.",
    "Grupo": "69: APARELHOS E ACESSÓRIOS PARA TREINAMENTO",
    "Classe": "6910: ACESSÓRIOS PARA TREINAMENTO",
    "PDM": "16111: OBRÉIA",
    "Status": "Ativo",
    "Sustentável": "Não"
  },
  {
    "Código do Item": 250678,
    "Descrição do Item": "OBRÉIA , MATERIAL PAPEL CELULOSE VEGETAL, FORMATO CIRCULAR, APRESENTAÇÃO AUTO ADESIVA, COR PRETA, TAMANHO PADRÃO, APLICAÇÃO COBRIR FUROS CAUSADOS POR PROJÉTEIS NOS ALVOS.",
    "Grupo": "69: APARELHOS E ACESSÓRIOS PARA TREINAMENTO",
    "Classe": "6910: ACESSÓRIOS PARA TREINAMENTO",
    "PDM": "16111: OBRÉIA",
    "Status": "Ativo",
    "Sustentável": "Não"
  },
  {
    "Código do Item": 251086,
    "Descrição do Item": "MODELO ANATÔMICO PARA FINS DIDÁTICOS , MATERIAL ACRÍLICO, TIPO DENTES DECÍDUOS, TAMANHO 12 X 6 CM, FINALIDADE MATERIAL EDUCATIVO ODONTOLÓGICO, TIPO ARCADA DENTÁRIA",
    "Grupo": "69: APARELHOS E ACESSÓRIOS PARA TREINAMENTO",
    "Classe": "6910: ACESSÓRIOS PARA TREINAMENTO",
    "PDM": "09837: MODELO ANATÔMICO PARA FINS DIDÁTICOS",
    "Status": "Ativo",
    "Sustentável": "Não"
  },
  {
    "Código do Item": 251279,
    "Descrição do Item": "MODELO ANATÔMICO PARA FINS DIDÁTICOS , MATERIAL ACRÍLICO, TAMANHO 13 X 7 CM, FINALIDADE MATERIAL EDUCATIVO ODONTOLÓGICO, TIPO MACRO ARCADA",
    "Grupo": "69: APARELHOS E ACESSÓRIOS PARA TREINAMENTO",
    "Classe": "6910: ACESSÓRIOS PARA TREINAMENTO",
    "PDM": "09837: MODELO ANATÔMICO PARA FINS DIDÁTICOS",
    "Status": "Inativo",
    "Sustentável": "Não"
  },
  {
    "Código do Item": 256847,
    "Descrição do Item": "MODELO TAMANHO REDUZIDO , TIPO MINI HIDRELÉTRICA, COMPONENTES MANGUEIRA PLÁSTICA, RODA D'ÁGUA, DÍNAMO DE TENSÃO, APLICAÇÃO AULAS DE ELETROMAGNETISMO",
    "Grupo": "69: APARELHOS E ACESSÓRIOS PARA TREINAMENTO",
    "Classe": "6910: ACESSÓRIOS PARA TREINAMENTO",
    "PDM": "09836: MODELO TAMANHO REDUZIDO",
    "Status": "Ativo",
    "Sustentável": "Não"
  },
  {
    "Código do Item": 256851,
    "Descrição do Item": "LUDIÃO , MATERIAL ACRÍLICO, CARACTERÍSTICAS ADICIONAIS COM O DIABRETE EM VIDRO E UMA ROLHA DE BORRACHA, APLICAÇÃO MECÂNICA DOS SÓLIDOS E DOS FLUIDOS",
    "Grupo": "69: APARELHOS E ACESSÓRIOS PARA TREINAMENTO",
    "Classe": "6910: ACESSÓRIOS PARA TREINAMENTO",
    "PDM": "16556: LUDIÃO",
    "Status": "Ativo",
    "Sustentável": "Não"
  },
  {
    "Código do Item": 256874,
    "Descrição do Item": "PONTEIRA - ESCRITA BRAILE , MATERIAL POLIPROPILENO INJETADO, FORMATO REDONDA, COMPRIMENTO 25 MM, DIÂMETRO 27,7 MM",
    "Grupo": "69: APARELHOS E ACESSÓRIOS PARA TREINAMENTO",
    "Classe": "6910: ACESSÓRIOS PARA TREINAMENTO",
    "PDM": "16560: PONTEIRA - ESCRITA BRAILE",
    "Status": "Ativo",
    "Sustentável": "Não"
  },
  {
    "Código do Item": 256875,
    "Descrição do Item": "PUNÇÃO - ESCRITA BRAILE , MATERIAL CABO PLÁSTICO, MATERIAL PONTEIRA AÇO, FORMATO ESFÉRICO, DIÂMETRO 25 MM",
    "Grupo": "69: APARELHOS E ACESSÓRIOS PARA TREINAMENTO",
    "Classe": "6910: ACESSÓRIOS PARA TREINAMENTO",
    "PDM": "16561: PUNÇÃO - ESCRITA BRAILE",
    "Status": "Ativo",
    "Sustentável": "Não"
  },
  {
    "Código do Item": 257082,
    "Descrição do Item": "CONJUNTO PLANETÁRIO , MATERIAL METAL, COMPONENTES TERRA, LUA E SOL, ACESSÓRIOS APOSTILA EXPLICATIVA, RELÓGIO DE SOL E BÚSSULA, APLICAÇÃO AULAS DE ASTRONOMIA",
    "Grupo": "69: APARELHOS E ACESSÓRIOS PARA TREINAMENTO",
    "Classe": "6910: ACESSÓRIOS PARA TREINAMENTO",
    "PDM": "16572: CONJUNTO PLANETÁRIO",
    "Status": "Ativo",
    "Sustentável": "Não"
  },
  {
    "Código do Item": 257086,
    "Descrição do Item": "GUIA ASSINATURA , MATERIAL ALUMÍNIO CROMADO E BORRACHA SILICÔNICA, APLICAÇÃO PRENCHIMENTO DE CHEQUES E OUTROS DOCUMENTOS POR, CARACTERÍSTICAS ADICIONAIS TRAVAS LATERAIS ANTIDERRAPANTES E ORIFÍCIO RETAN -",
    "Grupo": "69: APARELHOS E ACESSÓRIOS PARA TREINAMENTO",
    "Classe": "6910: ACESSÓRIOS PARA TREINAMENTO",
    "PDM": "16573: GUIA ASSINATURA",
    "Status": "Ativo",
    "Sustentável": "Não"
  },
  {
    "Código do Item": 257100,
    "Descrição do Item": "SOROBAN - DEFICIENTE VISUAL , MATERIAL PLÁSTICO, FORMATO RETANGULAR, COMPONENTES 21 EIXOS EM AÇO COM 1,5MM DE DIÂMETRO E 70MM DE, DIMENSÕES EXTERNAS 240X8X12 MM, CARACTERÍSTICAS ADICIONAIS SUPORTE ANTIDERRAPANTE INFERIOR E LATERAL, ESPONJA",
    "Grupo": "69: APARELHOS E ACESSÓRIOS PARA TREINAMENTO",
    "Classe": "6910: ACESSÓRIOS PARA TREINAMENTO",
    "PDM": "16575: SOROBAN - DEFICIENTE VISUAL",
    "Status": "Ativo",
    "Sustentável": "Não"
  },
  {
    "Código do Item": 257104,
    "Descrição do Item": "REGLETE - DEFICIENTE VISUAL , MATERIAL CHAPA METAL/ALUMÍNIO CROMADO, ESPESSURA 1,2 MM, MATERIAL PRANCHETA MDF, ESPESSURA PRANCHETA 10 MM, COMPONENTES PINOS INFERIORES, 4 LINHAS, 27 SELAS E PRANCHETA",
    "Grupo": "69: APARELHOS E ACESSÓRIOS PARA TREINAMENTO",
    "Classe": "6910: ACESSÓRIOS PARA TREINAMENTO",
    "PDM": "16576: REGLETE - DEFICIENTE VISUAL",
    "Status": "Ativo",
    "Sustentável": "Não"
  },
  {
    "Código do Item": 257178,
    "Descrição do Item": "MODELO ANATÔMICO PARA FINS DIDÁTICOS , MATERIAL SILICONE, FINALIDADE COM 4 VEIAS, TRES DELAS EM TAMANHOS DIFERENTES PAR, APLICAÇÃO TREINAMENTO",
    "Grupo": "69: APARELHOS E ACESSÓRIOS PARA TREINAMENTO",
    "Classe": "6910: ACESSÓRIOS PARA TREINAMENTO",
    "PDM": "09837: MODELO ANATÔMICO PARA FINS DIDÁTICOS",
    "Status": "Ativo",
    "Sustentável": "Não"
  },
  {
    "Código do Item": 257179,
    "Descrição do Item": "MODELO ANATÔMICO PARA FINS DIDÁTICOS , MATERIAL SILICONE, FINALIDADE RESSUSCITAÇÃO CARDIOPULMONAR, COM MANDÍBULA MÓVEL,, TIPO MANEQUIM ARTIFICIAL, APLICAÇÃO TREINAMENTO",
    "Grupo": "69: APARELHOS E ACESSÓRIOS PARA TREINAMENTO",
    "Classe": "6910: ACESSÓRIOS PARA TREINAMENTO",
    "PDM": "09837: MODELO ANATÔMICO PARA FINS DIDÁTICOS",
    "Status": "Ativo",
    "Sustentável": "Não"
  },
  {
    "Código do Item": 257180,
    "Descrição do Item": "MODELO ANATÔMICO PARA FINS DIDÁTICOS , FINALIDADE RESSUSCITAÇÃO CARDIOPULMONAR, COM TAMANHO E PESO C, TIPO MANEQUIM ARTIFICIAL, APLICAÇÃO TREINAMENTO",
    "Grupo": "69: APARELHOS E ACESSÓRIOS PARA TREINAMENTO",
    "Classe": "6910: ACESSÓRIOS PARA TREINAMENTO",
    "PDM": "09837: MODELO ANATÔMICO PARA FINS DIDÁTICOS",
    "Status": "Ativo",
    "Sustentável": "Não"
  },
  {
    "Código do Item": 257181,
    "Descrição do Item": "PISTA LOOPING , COMPONENTES COMPOSTA DE TRES TRECHOS, SENDO UMA RAMPA DESCENDE, FINALIDADE ESTUDO DO LANÇAMENTO OBLÍQUO E A CONSERVAÇÃO DA EN, APLICAÇÃO AULAS DE MECÂNICA CLÁSSICA",
    "Grupo": "69: APARELHOS E ACESSÓRIOS PARA TREINAMENTO",
    "Classe": "6910: ACESSÓRIOS PARA TREINAMENTO",
    "PDM": "16557: PISTA LOOPING",
    "Status": "Ativo",
    "Sustentável": "Não"
  },
  {
    "Código do Item": 257182,
    "Descrição do Item": "PÊNDULO DE NEWTON , COMPONENTES TRAVE MADEIRA E CINCO ESFERAS DE RESINA PLÁSTICA, FINALIDADE ILUSTRA O PRINCÍPIO DA CONSERVAÇÃO DA ENERGIA E MO, APLICAÇÃO AULAS DE MECÂNICA CLÁSSICA",
    "Grupo": "69: APARELHOS E ACESSÓRIOS PARA TREINAMENTO",
    "Classe": "6910: ACESSÓRIOS PARA TREINAMENTO",
    "PDM": "16586: PÊNDULO DE NEWTON",
    "Status": "Ativo",
    "Sustentável": "Não"
  },
  {
    "Código do Item": 257470,
    "Descrição do Item": "MODELO PARA ESTUDO , NOME MODELO PARA ESTUDO",
    "Grupo": "69: APARELHOS E ACESSÓRIOS PARA TREINAMENTO",
    "Classe": "6910: ACESSÓRIOS PARA TREINAMENTO",
    "PDM": "16607: MODELO PARA ESTUDO",
    "Status": "Inativo",
    "Sustentável": "Não"
  },
  {
    "Código do Item": 272107,
    "Descrição do Item": "EQUIPAMENTO DE INSTRUÇÃO , TIPO TRANSFORMADOR DESMONTÁVEL MASTER EQ182, MATERIAL COBRE CROMADO, MATERIAL BASE AÇO 1020, REVESTIMENTO EPÓXI, TENSÃO ALIMENTAÇÃO 0 A 250 V, CARACTERÍSTICAS ADICIONAIS ARMADURA LÂMINAS DE SILÍCIO, SELENÓIDE ESPIRALADO, APLICAÇÃO ESTUDO DAS SELENÓIDES, TRANSFORMADORES ELEVADORES",
    "Grupo": "69: APARELHOS E ACESSÓRIOS PARA TREINAMENTO",
    "Classe": "6910: ACESSÓRIOS PARA TREINAMENTO",
    "PDM": "09835: EQUIPAMENTO DE INSTRUÇÃO",
    "Status": "Ativo",
    "Sustentável": "Não"
  },
  {
    "Código do Item": 272108,
    "Descrição do Item": "EQUIPAMENTO DE INSTRUÇÃO , TIPO TRANSFORMADOR DESMONTÁVEL EQ170, MATERIAL COBRE CROMADO, MATERIAL BASE AÇO 1020, REVESTIMENTO EPÓXI, TENSÃO ALIMENTAÇÃO 0 A 250 V, CARACTERÍSTICAS ADICIONAIS ARMADURA LÂMINAS DE SILÍCIO, SELENÓIDE ESPIRALADO, APLICAÇÃO ESTUDO DAS SELENÓIDES, TRANSFORMADORES ELEVADORES",
    "Grupo": "69: APARELHOS E ACESSÓRIOS PARA TREINAMENTO",
    "Classe": "6910: ACESSÓRIOS PARA TREINAMENTO",
    "PDM": "09835: EQUIPAMENTO DE INSTRUÇÃO",
    "Status": "Ativo",
    "Sustentável": "Não"
  },
  {
    "Código do Item": 272609,
    "Descrição do Item": "BASE ALVO DE TIRO , MATERIAL MADEIRA, TAMANHO 4 X 4 X 170 CM, CARACTERÍSTICAS ADICIONAIS COMPOSTA DE DOIS ESTÁGIOS PARA SEREM FIXADOS NO SO, APLICAÇÃO TREINAMENTO",
    "Grupo": "69: APARELHOS E ACESSÓRIOS PARA TREINAMENTO",
    "Classe": "6920: ACESSÓRIOS PARA TREINAMENTO DE ARMAMENTO",
    "PDM": "02383: BASE ALVO DE TIRO",
    "Status": "Ativo",
    "Sustentável": "Não"
  },
  {
    "Código do Item": 272610,
    "Descrição do Item": "BASE ALVO DE TIRO , MATERIAL MADEIRA, TAMANHO 2 X 2 X 170 CM, CARACTERÍSTICAS ADICIONAIS COMPOSTA DE DOIS ESTÁGIOS PARA SEREM FIXADOS NO SO, APLICAÇÃO TREINAMENTO",
    "Grupo": "69: APARELHOS E ACESSÓRIOS PARA TREINAMENTO",
    "Classe": "6920: ACESSÓRIOS PARA TREINAMENTO DE ARMAMENTO",
    "PDM": "02383: BASE ALVO DE TIRO",
    "Status": "Ativo",
    "Sustentável": "Não"
  },
  {
    "Código do Item": 285012,
    "Descrição do Item": "ALVO DE TIRO , MATERIAL PAPELÃO, TIPO SILHUETA, TAMANHO 55 X 55 CM",
    "Grupo": "69: APARELHOS E ACESSÓRIOS PARA TREINAMENTO",
    "Classe": "6920: ACESSÓRIOS PARA TREINAMENTO DE ARMAMENTO",
    "PDM": "02382: ALVO DE TIRO",
    "Status": "Ativo",
    "Sustentável": "Não"
  },
  {
    "Código do Item": 285431,
    "Descrição do Item": "OBRÉIA , MATERIAL PAPEL CELULOSE VEGETAL, FORMATO CIRCULAR, APRESENTAÇÃO AUTO ADESIVA, COR PARDA, TAMANHO PADRÃO, APLICAÇÃO COBRIR FUROS CAUSADOS POR PROJÉTEIS NOS ALVOS.",
    "Grupo": "69: APARELHOS E ACESSÓRIOS PARA TREINAMENTO",
    "Classe": "6910: ACESSÓRIOS PARA TREINAMENTO",
    "PDM": "16111: OBRÉIA",
    "Status": "Ativo",
    "Sustentável": "Não"
  },
  {
    "Código do Item": 285433,
    "Descrição do Item": "ALVO DE TIRO , MATERIAL PAPELÃO, TIPO SILHUETA, TAMANHO 68 X 68 CM",
    "Grupo": "69: APARELHOS E ACESSÓRIOS PARA TREINAMENTO",
    "Classe": "6920: ACESSÓRIOS PARA TREINAMENTO DE ARMAMENTO",
    "PDM": "02382: ALVO DE TIRO",
    "Status": "Ativo",
    "Sustentável": "Não"
  },
  {
    "Código do Item": 285434,
    "Descrição do Item": "ALVO DE TIRO , MATERIAL PAPELÃO, TIPO SILHUETA COLT, TAMANHO 78 X 54 CM, CARACTERÍSTICAS ADICIONAIS COM GARRAFÃO CINZA",
    "Grupo": "69: APARELHOS E ACESSÓRIOS PARA TREINAMENTO",
    "Classe": "6920: ACESSÓRIOS PARA TREINAMENTO DE ARMAMENTO",
    "PDM": "02382: ALVO DE TIRO",
    "Status": "Ativo",
    "Sustentável": "Não"
  },
  {
    "Código do Item": 285435,
    "Descrição do Item": "ALVO DE TIRO , MATERIAL PAPELÃO, TIPO SILHUETA, TAMANHO 104 X 103 CM",
    "Grupo": "69: APARELHOS E ACESSÓRIOS PARA TREINAMENTO",
    "Classe": "6920: ACESSÓRIOS PARA TREINAMENTO DE ARMAMENTO",
    "PDM": "02382: ALVO DE TIRO",
    "Status": "Ativo",
    "Sustentável": "Não"
  },
  {
    "Código do Item": 295471,
    "Descrição do Item": "ALVO DE TIRO , MATERIAL CHAPA METÁLICA DE 1/2 POL, TIPO DISCO, CARACTERÍSTICAS ADICIONAIS HASTE VERGALHÃO DE 16MM X 1,40M DE ALTURA, DIÂMETRO 20 CM",
    "Grupo": "69: APARELHOS E ACESSÓRIOS PARA TREINAMENTO",
    "Classe": "6920: ACESSÓRIOS PARA TREINAMENTO DE ARMAMENTO",
    "PDM": "02382: ALVO DE TIRO",
    "Status": "Ativo",
    "Sustentável": "Não"
  },
  {
    "Código do Item": 309298,
    "Descrição do Item": "MODELO ANATÔMICO PARA FINS DIDÁTICOS , MATERIAL ACRÍLICO, FINALIDADE MATERIAL EDUCATIVO ODONTOLÓGICO, TIPO MACROARCADA/MACRO CÁRIE/MACRO PERIODONTAL, APLICAÇÃO TREINAMENTO, CARACTERÍSTICAS ADICIONAIS MACROESCOVA DENTAL COMPONDO O KIT ODONTOLÓGICO",
    "Grupo": "69: APARELHOS E ACESSÓRIOS PARA TREINAMENTO",
    "Classe": "6910: ACESSÓRIOS PARA TREINAMENTO",
    "PDM": "09837: MODELO ANATÔMICO PARA FINS DIDÁTICOS",
    "Status": "Ativo",
    "Sustentável": "Não"
  },
  {
    "Código do Item": 314577,
    "Descrição do Item": "KIT ELETRÔNICO , COMPONENTES TOMADA DE ENTRADA DE REDE C/3 PINOS,CHAVE LIGA/DES, REFERÊNCIA SCHURTER",
    "Grupo": "69: APARELHOS E ACESSÓRIOS PARA TREINAMENTO",
    "Classe": "6940: ACESSÓRIOS PARA TREINAMENTO DE COMUNICAÇÕES",
    "PDM": "08579: KIT ELETRÔNICO",
    "Status": "Ativo",
    "Sustentável": "Não"
  },
  {
    "Código do Item": 324112,
    "Descrição do Item": "MODELO ANATÔMICO PARA FINS DIDÁTICOS , MATERIAL POLIURETANO REVESTIDO DE POLIVINIL, FINALIDADE TÓRAX ALONGADO P/REANIMAÇÃO ADULTO,TIPO TRONCO, TIPO CABEÇA INCLINÁVEL P/ABRIR VIAS AÉREAS, APLICAÇÃO PTS ORIENTAÇÃO ANATÔMICOS(ESTERNO,TÓRAX,XIFÓIDE), CARACTERÍSTICAS ADICIONAIS MANOBRAS DE RESSUCITAÇÃO,3 PULMÕES,3 MÁSCARAS BOCA, OUTROS COMPONENTES BOLSA NYLON,ALMOFADA PARA JOELHO",
    "Grupo": "69: APARELHOS E ACESSÓRIOS PARA TREINAMENTO",
    "Classe": "6910: ACESSÓRIOS PARA TREINAMENTO",
    "PDM": "09837: MODELO ANATÔMICO PARA FINS DIDÁTICOS",
    "Status": "Ativo",
    "Sustentável": "Não"
  },
  {
    "Código do Item": 330384,
    "Descrição do Item": "MODELO ANATÔMICO PARA FINS DIDÁTICOS , ACESSÓRIOS SISTEMA PLATAFORMA MOLA, MATERIAL PLÁSTICO SILICONADO, FINALIDADE ENTUBAÇÃO TRAQUEAL INFANTIL C/SPRAY, TIPO MANEQUIM ARTIFICIAL, APLICAÇÃO ENTUBAÇÃO ORAL/NASAL,LUBRIFICANTE,MANUAL INSTRUÇÃO, CARACTERÍSTICAS ADICIONAIS ANATOMIA REALISTA ESTRUTURAS VIAS AÉREAS, OUTROS COMPONENTES TESTE INSUFLAÇÃO,TIPO PELE BEBÊ,CABEÇA COM BASE",
    "Grupo": "69: APARELHOS E ACESSÓRIOS PARA TREINAMENTO",
    "Classe": "6910: ACESSÓRIOS PARA TREINAMENTO",
    "PDM": "09837: MODELO ANATÔMICO PARA FINS DIDÁTICOS",
    "Status": "Ativo",
    "Sustentável": "Não"
  },
  {
    "Código do Item": 330385,
    "Descrição do Item": "MODELO ANATÔMICO PARA FINS DIDÁTICOS , ACESSÓRIOS BULBO SIMULAÇÃO BRAQUIAL,MONITOR TP SKILLGUIDE, FINALIDADE REANIMAÇÃO NEONATAL,1 PULMÃO EXTRA, TIPO MANEQUIM ARTIFICIAL, APLICAÇÃO MALETA PLÁSTICO,2 FACES ADCIONAIS,5 VAS,6 LENÇOS, CARACTERÍSTICAS ADICIONAIS DESOBSTRUÇÃO VIAS AÉREAS,SIMULAÇÃO PULSO BRAQUIAL, OUTROS COMPONENTES VAS DESCARTÁVEIS,FACES REMOVÍVEIS E REUSÁVEIS",
    "Grupo": "69: APARELHOS E ACESSÓRIOS PARA TREINAMENTO",
    "Classe": "6910: ACESSÓRIOS PARA TREINAMENTO",
    "PDM": "09837: MODELO ANATÔMICO PARA FINS DIDÁTICOS",
    "Status": "Ativo",
    "Sustentável": "Não"
  },
  {
    "Código do Item": 336758,
    "Descrição do Item": "ALVO DE TIRO , MATERIAL PAPELÃO, TIPO SILHUETA, TAMANHO 96 X 50 CM",
    "Grupo": "69: APARELHOS E ACESSÓRIOS PARA TREINAMENTO",
    "Classe": "6920: ACESSÓRIOS PARA TREINAMENTO DE ARMAMENTO",
    "PDM": "02382: ALVO DE TIRO",
    "Status": "Ativo",
    "Sustentável": "Não"
  },
  {
    "Código do Item": 336854,
    "Descrição do Item": "ALVO DE TIRO , MATERIAL PAPELÃO, TIPO SILHUETA, TAMANHO 6,30 X 12,50 CM, CARACTERÍSTICAS ADICIONAIS SILHUETA PRETA",
    "Grupo": "69: APARELHOS E ACESSÓRIOS PARA TREINAMENTO",
    "Classe": "6920: ACESSÓRIOS PARA TREINAMENTO DE ARMAMENTO",
    "PDM": "02382: ALVO DE TIRO",
    "Status": "Ativo",
    "Sustentável": "Não"
  },
  {
    "Código do Item": 342183,
    "Descrição do Item": "MODELO ANATÔMICO PARA FINS DIDÁTICOS , MATERIAL PRANCHA MADEIRA FORRADA, TAMANHO 21 X 29,50 X 20 CM, FINALIDADE ENSAIO AMAMENTAÇÃO, ORDENHA E AUTO-EXAME, TIPO SEIO NA PRANCHA, APLICAÇÃO TREINAMENTO, CARACTERÍSTICAS ADICIONAIS ACABAMENTO CROCHÊ, ALÇA/CORDÃO REGULÁVEL, MORENA E",
    "Grupo": "69: APARELHOS E ACESSÓRIOS PARA TREINAMENTO",
    "Classe": "6910: ACESSÓRIOS PARA TREINAMENTO",
    "PDM": "09837: MODELO ANATÔMICO PARA FINS DIDÁTICOS",
    "Status": "Ativo",
    "Sustentável": "Não"
  },
  {
    "Código do Item": 357287,
    "Descrição do Item": "MODELO ANATÔMICO PARA FINS DIDÁTICOS , MATERIAL SILICONE, FINALIDADE TREINAMENTO DE INJEÇÃO INTRAMUSCULAR, TIPO NÁDEGAS COR DA PELE",
    "Grupo": "69: APARELHOS E ACESSÓRIOS PARA TREINAMENTO",
    "Classe": "6910: ACESSÓRIOS PARA TREINAMENTO",
    "PDM": "09837: MODELO ANATÔMICO PARA FINS DIDÁTICOS",
    "Status": "Ativo",
    "Sustentável": "Não"
  },
  {
    "Código do Item": 359052,
    "Descrição do Item": "MODELO ANATÔMICO PARA FINS DIDÁTICOS , MATERIAL RESINA PLÁSTICA, FINALIDADE FUNCIONAL DE ARTICULAÇÃO DE JOELHO FLEXÍVEL, TIPO PATELA, PARTES DO FÊMUR, TÍBIA E FÍBULA, CARACTERÍSTICAS ADICIONAIS MENISCOS, TENDÕES E LIGAMENTOS",
    "Grupo": "69: APARELHOS E ACESSÓRIOS PARA TREINAMENTO",
    "Classe": "6910: ACESSÓRIOS PARA TREINAMENTO",
    "PDM": "09837: MODELO ANATÔMICO PARA FINS DIDÁTICOS",
    "Status": "Ativo",
    "Sustentável": "Não"
  },
  {
    "Código do Item": 359061,
    "Descrição do Item": "MODELO ANATÔMICO PARA FINS DIDÁTICOS , MATERIAL RESINA PLÁSTICA, FINALIDADE FUNCIONAL DE ARTICULAÇÃO DE JOELHO FLEXÍVEL, TIPO COMPOSTO 5 VÉRTEBRAS LOMBARES,DISCO INVERTEBRAL, CARACTERÍSTICAS ADICIONAIS SACRO C/ BORDAS, CÓCCIX, OUTROS COMPONENTES VÉRTEBRAS C/ PROLAPSO ENTRE 2º E 3º VÉRTEBRAS",
    "Grupo": "69: APARELHOS E ACESSÓRIOS PARA TREINAMENTO",
    "Classe": "6910: ACESSÓRIOS PARA TREINAMENTO",
    "PDM": "09837: MODELO ANATÔMICO PARA FINS DIDÁTICOS",
    "Status": "Ativo",
    "Sustentável": "Não"
  },
  {
    "Código do Item": 363108,
    "Descrição do Item": "MODELO ANATÔMICO PARA FINS DIDÁTICOS , MATERIAL GESSO PINTADO, FINALIDADE ESTUDO DE EMBRIÕES HUMANOS, TIPO MÓRULA, BLASTOCELE, HIPOBLASTO, AMNIOGÊNESE",
    "Grupo": "69: APARELHOS E ACESSÓRIOS PARA TREINAMENTO",
    "Classe": "6910: ACESSÓRIOS PARA TREINAMENTO",
    "PDM": "09837: MODELO ANATÔMICO PARA FINS DIDÁTICOS",
    "Status": "Ativo",
    "Sustentável": "Não"
  },
  {
    "Código do Item": 363109,
    "Descrição do Item": "MODELO ANATÔMICO PARA FINS DIDÁTICOS , MATERIAL GESSO PINTADO, FINALIDADE ESTUDO DE EMBRIÕES HUMANOS, TIPO IMPLANTAÇÃO INSTERSTICIAL, SACO VITELINO, OUTROS COMPONENTES FORMAÇÃO MESODERMA EXTRAEMBRIONÁRIO E CÓRIO",
    "Grupo": "69: APARELHOS E ACESSÓRIOS PARA TREINAMENTO",
    "Classe": "6910: ACESSÓRIOS PARA TREINAMENTO",
    "PDM": "09837: MODELO ANATÔMICO PARA FINS DIDÁTICOS",
    "Status": "Ativo",
    "Sustentável": "Não"
  },
  {
    "Código do Item": 363110,
    "Descrição do Item": "MODELO ANATÔMICO PARA FINS DIDÁTICOS , MATERIAL GESSO PINTADO, FINALIDADE ESTUDO DE EMBRIÕES HUMANOS, TIPO FASE INICIAL E INTERMEDIÁRIA GASTRULAÇÃO, OUTROS COMPONENTES FORMAÇÃO DO ALANTÓIDE E PLACA NEURAL",
    "Grupo": "69: APARELHOS E ACESSÓRIOS PARA TREINAMENTO",
    "Classe": "6910: ACESSÓRIOS PARA TREINAMENTO",
    "PDM": "09837: MODELO ANATÔMICO PARA FINS DIDÁTICOS",
    "Status": "Ativo",
    "Sustentável": "Não"
  },
  {
    "Código do Item": 363111,
    "Descrição do Item": "MODELO ANATÔMICO PARA FINS DIDÁTICOS , MATERIAL GESSO PINTADO, FINALIDADE ESTUDO DE EMBRIÕES HUMANOS, TIPO CORTES SAGITAIS EMBRIÃO FASE DISCOIDAL, OUTROS COMPONENTES NAS MEMBRANAS EMBRIONÁRIAS",
    "Grupo": "69: APARELHOS E ACESSÓRIOS PARA TREINAMENTO",
    "Classe": "6910: ACESSÓRIOS PARA TREINAMENTO",
    "PDM": "09837: MODELO ANATÔMICO PARA FINS DIDÁTICOS",
    "Status": "Ativo",
    "Sustentável": "Não"
  },
  {
    "Código do Item": 363112,
    "Descrição do Item": "MODELO ANATÔMICO PARA FINS DIDÁTICOS , ACESSÓRIOS VISUALIZAÇÃO DO TUBO E CRISTA NEURAL, MATERIAL GESSO PINTADO, FINALIDADE ESTUDO DE EMBRIÕES HUMANOS, TIPO FORMAÇÃO SISTEMA NERVOSO, CORTE TRANSVERSAL DISCO, OUTROS COMPONENTES FORMAÇÃO TUBO NEURAL, CORTE TRANSVERSAL",
    "Grupo": "69: APARELHOS E ACESSÓRIOS PARA TREINAMENTO",
    "Classe": "6910: ACESSÓRIOS PARA TREINAMENTO",
    "PDM": "09837: MODELO ANATÔMICO PARA FINS DIDÁTICOS",
    "Status": "Ativo",
    "Sustentável": "Não"
  },
  {
    "Código do Item": 363113,
    "Descrição do Item": "MODELO ANATÔMICO PARA FINS DIDÁTICOS , MATERIAL GESSO PINTADO, FINALIDADE ESTUDO DE EMBRIÕES HUMANOS, TIPO CORTE TRANSVERSAL DO EMBRIÃO FORMA CILÍNDRICA, OUTROS COMPONENTES 1/3 MÉDIO E REGIÃO ANTERIOR/POSTERIOR",
    "Grupo": "69: APARELHOS E ACESSÓRIOS PARA TREINAMENTO",
    "Classe": "6910: ACESSÓRIOS PARA TREINAMENTO",
    "PDM": "09837: MODELO ANATÔMICO PARA FINS DIDÁTICOS",
    "Status": "Ativo",
    "Sustentável": "Não"
  },
  {
    "Código do Item": 363114,
    "Descrição do Item": "MODELO ANATÔMICO PARA FINS DIDÁTICOS , MATERIAL GESSO PINTADO, FINALIDADE ESTUDO DE EMBRIÕES HUMANOS, TIPO EMBRIÃO CILÍNDRICO 4 SEMANAS MEMBRANAS EXTRAEMBRI., OUTROS COMPONENTES CORTE LONGITUDINAL DO EMBRIÃO 4 E 5 SEMANAS",
    "Grupo": "69: APARELHOS E ACESSÓRIOS PARA TREINAMENTO",
    "Classe": "6910: ACESSÓRIOS PARA TREINAMENTO",
    "PDM": "09837: MODELO ANATÔMICO PARA FINS DIDÁTICOS",
    "Status": "Ativo",
    "Sustentável": "Não"
  },
  {
    "Código do Item": 372026,
    "Descrição do Item": "ALVO DE TIRO , MATERIAL PAPEL OFFSETE 90 GR, TIPO QUADRADO, TAMANHO 1,80 X 1,80 M, CARACTERÍSTICAS ADICIONAIS ALVO PARA FUZIL",
    "Grupo": "69: APARELHOS E ACESSÓRIOS PARA TREINAMENTO",
    "Classe": "6920: ACESSÓRIOS PARA TREINAMENTO DE ARMAMENTO",
    "PDM": "02382: ALVO DE TIRO",
    "Status": "Ativo",
    "Sustentável": "Não"
  },
  {
    "Código do Item": 372027,
    "Descrição do Item": "ALVO DE TIRO , MATERIAL PAPEL OFFSETE 90 GR, TIPO RETANGULAR, TAMANHO 1,20 X 1,80 M, CARACTERÍSTICAS ADICIONAIS ALVO PARA FUZIL",
    "Grupo": "69: APARELHOS E ACESSÓRIOS PARA TREINAMENTO",
    "Classe": "6920: ACESSÓRIOS PARA TREINAMENTO DE ARMAMENTO",
    "PDM": "02382: ALVO DE TIRO",
    "Status": "Ativo",
    "Sustentável": "Não"
  },
  {
    "Código do Item": 372029,
    "Descrição do Item": "ALVO DE TIRO , MATERIAL PAPEL OFFSETE 90 GR, TIPO SILHUETA, TAMANHO 47,50 X 158 CM",
    "Grupo": "69: APARELHOS E ACESSÓRIOS PARA TREINAMENTO",
    "Classe": "6920: ACESSÓRIOS PARA TREINAMENTO DE ARMAMENTO",
    "PDM": "02382: ALVO DE TIRO",
    "Status": "Ativo",
    "Sustentável": "Não"
  },
  {
    "Código do Item": 373342,
    "Descrição do Item": "MODELO ANATÔMICO PARA FINS DIDÁTICOS , ACESSÓRIOS PAINEL ELETRÔNICO, VESTIMENTA, MATERIAL POLIURETANO REVESTIDO DE POLIVINIL, FINALIDADE TREINAMENTO RCP, TIPO CABEÇA INCLINÁVEL P/ABRIR VIAS AÉREAS, CARACTERÍSTICAS ADICIONAIS PTS ANATÔMICOS PROCESSO XIFÓIDE, 2 PULMÕES DESCAR",
    "Grupo": "69: APARELHOS E ACESSÓRIOS PARA TREINAMENTO",
    "Classe": "6910: ACESSÓRIOS PARA TREINAMENTO",
    "PDM": "09837: MODELO ANATÔMICO PARA FINS DIDÁTICOS",
    "Status": "Ativo",
    "Sustentável": "Não"
  },
  {
    "Código do Item": 375291,
    "Descrição do Item": "MODELO ANATÔMICO PARA FINS DIDÁTICOS , MATERIAL RESINA PLÁSTICA RÍGIDA, TIPO ARTICULAÇÃO OMBRO, CARACTERÍSTICAS ADICIONAIS CLAVÍCULA, ESCÁPULA, CABEÇA ÚMERO, OUTROS COMPONENTES LIGAMENTOS ARTICULARES",
    "Grupo": "69: APARELHOS E ACESSÓRIOS PARA TREINAMENTO",
    "Classe": "6910: ACESSÓRIOS PARA TREINAMENTO",
    "PDM": "09837: MODELO ANATÔMICO PARA FINS DIDÁTICOS",
    "Status": "Ativo",
    "Sustentável": "Não"
  },
  {
    "Código do Item": 375292,
    "Descrição do Item": "MODELO ANATÔMICO PARA FINS DIDÁTICOS , MATERIAL RESINA PLÁSTICA RÍGIDA, TIPO ARTICULAÇÃO QUADRIL, CARACTERÍSTICAS ADICIONAIS PARTE DO FÊMUR E OSSO DO QUADRIL, OUTROS COMPONENTES LIGAMENTOS ARTICULARES",
    "Grupo": "69: APARELHOS E ACESSÓRIOS PARA TREINAMENTO",
    "Classe": "6910: ACESSÓRIOS PARA TREINAMENTO",
    "PDM": "09837: MODELO ANATÔMICO PARA FINS DIDÁTICOS",
    "Status": "Ativo",
    "Sustentável": "Não"
  },
  {
    "Código do Item": 375294,
    "Descrição do Item": "MODELO ANATÔMICO PARA FINS DIDÁTICOS , MATERIAL RESINA PLÁSTICA RÍGIDA, TIPO ARTICULAÇÃO PÉ, CARACTERÍSTICAS ADICIONAIS CALCÂNEO, ASTRALAGO, CUBÓIDE, ESCAFÓIDE,CUNEIFORME, OUTROS COMPONENTES LIGAMENTOS ARTICULARES",
    "Grupo": "69: APARELHOS E ACESSÓRIOS PARA TREINAMENTO",
    "Classe": "6910: ACESSÓRIOS PARA TREINAMENTO",
    "PDM": "09837: MODELO ANATÔMICO PARA FINS DIDÁTICOS",
    "Status": "Ativo",
    "Sustentável": "Não"
  },
  {
    "Código do Item": 375295,
    "Descrição do Item": "MODELO ANATÔMICO PARA FINS DIDÁTICOS , MATERIAL RESINA PLÁSTICA RÍGIDA, TIPO ARTICULAÇÃO JOELHO, CARACTERÍSTICAS ADICIONAIS PARTE FÊMUR, PATELA, ARTICULAÇÃO TÍBIA E FÍBULA, OUTROS COMPONENTES LIGAMENTOS ARTICULARES",
    "Grupo": "69: APARELHOS E ACESSÓRIOS PARA TREINAMENTO",
    "Classe": "6910: ACESSÓRIOS PARA TREINAMENTO",
    "PDM": "09837: MODELO ANATÔMICO PARA FINS DIDÁTICOS",
    "Status": "Ativo",
    "Sustentável": "Não"
  },
  {
    "Código do Item": 375296,
    "Descrição do Item": "MODELO ANATÔMICO PARA FINS DIDÁTICOS , MATERIAL RESINA PLÁSTICA RÍGIDA, TIPO ARTICULÇÃO COTOVELO, CARACTERÍSTICAS ADICIONAIS PARTE DO ÚMERO, CÚBITO E RÁDIO, OUTROS COMPONENTES LIGAMENTOS ARTICULARES",
    "Grupo": "69: APARELHOS E ACESSÓRIOS PARA TREINAMENTO",
    "Classe": "6910: ACESSÓRIOS PARA TREINAMENTO",
    "PDM": "09837: MODELO ANATÔMICO PARA FINS DIDÁTICOS",
    "Status": "Ativo",
    "Sustentável": "Não"
  },
  {
    "Código do Item": 375297,
    "Descrição do Item": "MODELO ANATÔMICO PARA FINS DIDÁTICOS , MATERIAL RESINA PLÁSTICA RÍGIDA, TIPO ARTICULAÇÃO MÃO, CARACTERÍSTICAS ADICIONAIS METACARPOS, FALANGES, E PEQUENOS OSSOS, OUTROS COMPONENTES LIGAMENTOS ARTICULARES",
    "Grupo": "69: APARELHOS E ACESSÓRIOS PARA TREINAMENTO",
    "Classe": "6910: ACESSÓRIOS PARA TREINAMENTO",
    "PDM": "09837: MODELO ANATÔMICO PARA FINS DIDÁTICOS",
    "Status": "Ativo",
    "Sustentável": "Não"
  },
  {
    "Código do Item": 375298,
    "Descrição do Item": "MODELO ANATÔMICO PARA FINS DIDÁTICOS , ACESSÓRIOS SUPORTE COM RODAS, MATERIAL RESINA PLÁSTICA RÍGIDA, TAMANHO 75 X 44 X 44 CM, TIPO ESQUELETO HUMANO, CARACTERÍSTICAS ADICIONAIS COMPLETO COM DETALHES ANATÔMICOS, OUTROS COMPONENTES LIGAMENTOS ARTICULARES",
    "Grupo": "69: APARELHOS E ACESSÓRIOS PARA TREINAMENTO",
    "Classe": "6910: ACESSÓRIOS PARA TREINAMENTO",
    "PDM": "09837: MODELO ANATÔMICO PARA FINS DIDÁTICOS",
    "Status": "Ativo",
    "Sustentável": "Não"
  },
  {
    "Código do Item": 381672,
    "Descrição do Item": "OBRÉIA , MATERIAL PAPEL CELULOSE VEGETAL, FORMATO CIRCULAR, APRESENTAÇÃO AUTO ADESIVA, COR VERDE, APLICAÇÃO COBRIR FUROS CAUSADOS POR PROJÉTEIS NOS ALVOS.",
    "Grupo": "69: APARELHOS E ACESSÓRIOS PARA TREINAMENTO",
    "Classe": "6910: ACESSÓRIOS PARA TREINAMENTO",
    "PDM": "16111: OBRÉIA",
    "Status": "Ativo",
    "Sustentável": "Não"
  },
  {
    "Código do Item": 381673,
    "Descrição do Item": "OBRÉIA , MATERIAL PAPEL CELULOSE VEGETAL, FORMATO CIRCULAR, APRESENTAÇÃO AUTO ADESIVA, COR AMARELA, APLICAÇÃO COBRIR FUROS CAUSADOS POR PROJÉTEIS NOS ALVOS.",
    "Grupo": "69: APARELHOS E ACESSÓRIOS PARA TREINAMENTO",
    "Classe": "6910: ACESSÓRIOS PARA TREINAMENTO",
    "PDM": "16111: OBRÉIA",
    "Status": "Ativo",
    "Sustentável": "Não"
  },
  {
    "Código do Item": 381674,
    "Descrição do Item": "OBRÉIA , MATERIAL PAPEL CELULOSE VEGETAL, FORMATO CIRCULAR, APRESENTAÇÃO AUTO ADESIVA, COR VERMELHA, APLICAÇÃO COBRIR FUROS CAUSADOS POR PROJÉTEIS NOS ALVOS.",
    "Grupo": "69: APARELHOS E ACESSÓRIOS PARA TREINAMENTO",
    "Classe": "6910: ACESSÓRIOS PARA TREINAMENTO",
    "PDM": "16111: OBRÉIA",
    "Status": "Ativo",
    "Sustentável": "Não"
  },
  {
    "Código do Item": 381675,
    "Descrição do Item": "OBRÉIA , MATERIAL PAPEL CELULOSE VEGETAL, FORMATO CIRCULAR, APRESENTAÇÃO AUTO ADESIVA, COR DIVERSAS, APLICAÇÃO COBRIR FUROS CAUSADOS POR PROJÉTEIS NOS ALVOS.",
    "Grupo": "69: APARELHOS E ACESSÓRIOS PARA TREINAMENTO",
    "Classe": "6910: ACESSÓRIOS PARA TREINAMENTO",
    "PDM": "16111: OBRÉIA",
    "Status": "Ativo",
    "Sustentável": "Não"
  },
  {
    "Código do Item": 382758,
    "Descrição do Item": "MODELO ANATÔMICO PARA FINS DIDÁTICOS , ACESSÓRIOS PITEIRA AÇO INOX, CAIXA COM ALÇA TRANSPORTE, MATERIAL BASE MADEIRA, CORPO ACRÍLICO, CABEÇA VINIL, FINALIDADE INDICA DANOS DA NICOTINA NO PULMÃO, TIPO BONECA FUMANTE, CARACTERÍSTICAS ADICIONAIS BORDAS POLIDAS, BOMBA PNEUMÁTICA PARTE POSTERIOR",
    "Grupo": "69: APARELHOS E ACESSÓRIOS PARA TREINAMENTO",
    "Classe": "6910: ACESSÓRIOS PARA TREINAMENTO",
    "PDM": "09837: MODELO ANATÔMICO PARA FINS DIDÁTICOS",
    "Status": "Ativo",
    "Sustentável": "Não"
  },
  {
    "Código do Item": 391195,
    "Descrição do Item": "MODELO ANATÔMICO PARA FINS DIDÁTICOS , ACESSÓRIOS ESTETOSCÓPIO, MALETA E CONTROLE REMOTO, MATERIAL LÁTEX, FINALIDADE RCP, AUSCULTA E ENTUBAÇÃO NEONATAL, TIPO CUIDADOS UMBILICAIS, CARACTERÍSTICAS ADICIONAIS GERADOR MANUAL PULSO BRAQUIAL, CORAÇÃO, INTESTINO, OUTROS COMPONENTES 2 PONTOS PULMÃO ANTERIOR E 2 POSTERIOR",
    "Grupo": "69: APARELHOS E ACESSÓRIOS PARA TREINAMENTO",
    "Classe": "6910: ACESSÓRIOS PARA TREINAMENTO",
    "PDM": "09837: MODELO ANATÔMICO PARA FINS DIDÁTICOS",
    "Status": "Ativo",
    "Sustentável": "Não"
  },
  {
    "Código do Item": 391768,
    "Descrição do Item": "MODELO ANATÔMICO PARA FINS DIDÁTICOS , ACESSÓRIOS MALETA TRANSPORTE, MATERIAL SILICONE, TIPO BRAÇO ARTIFICIAL, APLICAÇÃO INJEÇÕES INTRAMUSCULARES, VENOSAS E SUBCUTÂNEAS, CARACTERÍSTICAS ADICIONAIS SISTEMA VASCULAR RAMIFICADO, PONTOS P/ INJEÇÕES SU, OUTROS COMPONENTES SANGUE ARTIFICIAL, SERINGA, AGULHA",
    "Grupo": "69: APARELHOS E ACESSÓRIOS PARA TREINAMENTO",
    "Classe": "6910: ACESSÓRIOS PARA TREINAMENTO",
    "PDM": "09837: MODELO ANATÔMICO PARA FINS DIDÁTICOS",
    "Status": "Ativo",
    "Sustentável": "Não"
  },
  {
    "Código do Item": 391769,
    "Descrição do Item": "EQUIPAMENTO DE INSTRUÇÃO , TIPO LIGAÇÃO DE SIMULADOR DE RESSUSCITAÇÃO CARDIOPULMON, MATERIAL METAL, CARACTERÍSTICAS ADICIONAIS ARMAZENAGEM, IMPRESSÃO DADOS, COMPRESSÕES ADMINIS, APLICAÇÃO LIGAR O SIMULADOR DE RESSUSCITAÇÃO AO COMPUTADOR",
    "Grupo": "69: APARELHOS E ACESSÓRIOS PARA TREINAMENTO",
    "Classe": "6910: ACESSÓRIOS PARA TREINAMENTO",
    "PDM": "09835: EQUIPAMENTO DE INSTRUÇÃO",
    "Status": "Ativo",
    "Sustentável": "Não"
  },
  {
    "Código do Item": 391770,
    "Descrição do Item": "MODELO ANATÔMICO PARA FINS DIDÁTICOS , ACESSÓRIOS MALETA TRANSPORTE, MATERIAL SILICONE, FINALIDADE MANEJO INTRA-UTERINO, PRÉ-NATAIS, INTRAPARTO, PÓS-, TIPO CAVIDA PÉLVICA COM VÉRTICES E NÁDEGAS, APLICAÇÃO SIMULAÇÃO PARTO NORMAL E CESARIANA, CARACTERÍSTICAS ADICIONAIS PLACENTA,PROLAPSO,CORDÃO UMBILICAL,MANOBRA RITGEN,, OUTROS COMPONENTES REVESTIMENTO ABDÔMEN, FETO MASCULINO E FEMININO,",
    "Grupo": "69: APARELHOS E ACESSÓRIOS PARA TREINAMENTO",
    "Classe": "6910: ACESSÓRIOS PARA TREINAMENTO",
    "PDM": "09837: MODELO ANATÔMICO PARA FINS DIDÁTICOS",
    "Status": "Ativo",
    "Sustentável": "Não"
  },
  {
    "Código do Item": 391772,
    "Descrição do Item": "MODELO ANATÔMICO PARA FINS DIDÁTICOS , ACESSÓRIOS MALETA TRANSPORTE, MATERIAL ELÁSTICO, FINALIDADE DIAGNÓSTICO PATOLÓGICO, TIPO CABEÇA COM 6 ORELHAS SUBSTITUÍVEIS, APLICAÇÃO REMOÇÃO DE CERUME, CARACTERÍSTICAS ADICIONAIS SLIDES CONDIÇÕES PATOLÓGICAS, OUTROS COMPONENTES CERUME ARTIFICIAL, SLIDES",
    "Grupo": "69: APARELHOS E ACESSÓRIOS PARA TREINAMENTO",
    "Classe": "6910: ACESSÓRIOS PARA TREINAMENTO",
    "PDM": "09837: MODELO ANATÔMICO PARA FINS DIDÁTICOS",
    "Status": "Ativo",
    "Sustentável": "Não"
  },
  {
    "Código do Item": 391774,
    "Descrição do Item": "MODELO ANATÔMICO PARA FINS DIDÁTICOS , ACESSÓRIOS LUZ INDICADOR DE PULSO, MATERIAL METAL, TIPO SIMULADOR ARRITMIAS, APLICAÇÃO RITMOS CARDÍACOS E ARRITIMIAS ADULTO E PEDIÁTRICO, CARACTERÍSTICAS ADICIONAIS CARDIOVERSÃO, FIBRILAÇÃO E FLUTER ATRIAL",
    "Grupo": "69: APARELHOS E ACESSÓRIOS PARA TREINAMENTO",
    "Classe": "6910: ACESSÓRIOS PARA TREINAMENTO",
    "PDM": "09837: MODELO ANATÔMICO PARA FINS DIDÁTICOS",
    "Status": "Ativo",
    "Sustentável": "Não"
  },
  {
    "Código do Item": 391775,
    "Descrição do Item": "MODELO ANATÔMICO PARA FINS DIDÁTICOS , ACESSÓRIOS BOLSA PARA TRANSPORTE, MATERIAL SILICONE, FINALIDADE MONITORAÇÃO POR ECG, PULSO DA ARTÉRIA BRAQUIAL, TIPO MANEQUIM SIMULADOR ECG INFANTIL, APLICAÇÃO VENTILAÇÃO ARTIFICIAL, INTUBAÇÃO ORAL / NASAL, CARACTERÍSTICAS ADICIONAIS MASSAGEM CARDÍACA, MANDÍBULA MÓVEL, ACESSOS VENOSO, OUTROS COMPONENTES INTRODUÇÃO ÓSSEA DE AGULHAS,PULSÃO DE MEDULA ÓSSEA",
    "Grupo": "69: APARELHOS E ACESSÓRIOS PARA TREINAMENTO",
    "Classe": "6910: ACESSÓRIOS PARA TREINAMENTO",
    "PDM": "09837: MODELO ANATÔMICO PARA FINS DIDÁTICOS",
    "Status": "Ativo",
    "Sustentável": "Não"
  },
  {
    "Código do Item": 391776,
    "Descrição do Item": "MODELO ANATÔMICO PARA FINS DIDÁTICOS , ACESSÓRIOS COLAR CERVICAL, MEMBRANA CRICOTIREÓIDE, MATERIAL SILICONE, FINALIDADE TREINAMENTO DE EMERGÊNCIA, TIPO MANEQUIM ADULTO, APLICAÇÃO ARRITMIAS, ACESSO VIAS AÉREAS, ASCUTA ESTOMACAL, CARACTERÍSTICAS ADICIONAIS PULSO CARÓTIDA, MONITORAÇÃO CARDÍACA, OUTROS COMPONENTES LÍNGUA INFLÁVEL, COMPRESSÃO PEITO FECHADO",
    "Grupo": "69: APARELHOS E ACESSÓRIOS PARA TREINAMENTO",
    "Classe": "6910: ACESSÓRIOS PARA TREINAMENTO",
    "PDM": "09837: MODELO ANATÔMICO PARA FINS DIDÁTICOS",
    "Status": "Ativo",
    "Sustentável": "Não"
  },
  {
    "Código do Item": 391777,
    "Descrição do Item": "MODELO ANATÔMICO PARA FINS DIDÁTICOS , ACESSÓRIOS MÁSCARA FACIAL, MAL, VESTIMENTA, MATERIAL SILICONE, FINALIDADE MEDIDAS BÁSICAS DE RCP, TIPO MANEQUIM ADULTO, APLICAÇÃO OBSTRUÇÃO VIAS AÉREAS, MANDÍBULA MÓVEL, CARACTERÍSTICAS ADICIONAIS VÁLVULA RETENÇÃO E ANTI-REFLUXO, EXPANSÃO TÓRAX, P",
    "Grupo": "69: APARELHOS E ACESSÓRIOS PARA TREINAMENTO",
    "Classe": "6910: ACESSÓRIOS PARA TREINAMENTO",
    "PDM": "09837: MODELO ANATÔMICO PARA FINS DIDÁTICOS",
    "Status": "Ativo",
    "Sustentável": "Não"
  },
  {
    "Código do Item": 391779,
    "Descrição do Item": "MODELO ANATÔMICO PARA FINS DIDÁTICOS , ACESSÓRIOS OLHOS MÓVEIS, RCP, MATERIAL SILICONE, FINALIDADE PRÁTICA HIGIENE BUCAL E OUTRAS, TIPO MANEQUIM ADULTO, APLICAÇÃO ACESSO INTRAVENOSO,INTRAMUSCULAR,SUBCUTÂNEA,OSTOMI, CARACTERÍSTICAS ADICIONAIS LAVAGEM GÁSTRICA E VAGINAL,CATETERIZAÇÃO,EXAME PRÓ",
    "Grupo": "69: APARELHOS E ACESSÓRIOS PARA TREINAMENTO",
    "Classe": "6910: ACESSÓRIOS PARA TREINAMENTO",
    "PDM": "09837: MODELO ANATÔMICO PARA FINS DIDÁTICOS",
    "Status": "Ativo",
    "Sustentável": "Não"
  },
  {
    "Código do Item": 391780,
    "Descrição do Item": "MODELO ANATÔMICO PARA FINS DIDÁTICOS , MATERIAL SILICONE, FINALIDADE DETERMINAÇÃO PRESSÃO SANGUÍNEA, TIPO BRAÇO COMESFIGMOMANÔMETRO, APLICAÇÃO IDENTIFICAR FASES DE SONS DE KOROTOFF, CARACTERÍSTICAS ADICIONAIS COM UNIDADE ELETRÔNICA",
    "Grupo": "69: APARELHOS E ACESSÓRIOS PARA TREINAMENTO",
    "Classe": "6910: ACESSÓRIOS PARA TREINAMENTO",
    "PDM": "09837: MODELO ANATÔMICO PARA FINS DIDÁTICOS",
    "Status": "Ativo",
    "Sustentável": "Não"
  },
  {
    "Código do Item": 392903,
    "Descrição do Item": "MODELO ANATÔMICO PARA FINS DIDÁTICOS , ACESSÓRIOS BOLSA PARA TRANSPORTE, MATERIAL SILICONE, FINALIDADE SIMULADOR SEIO FEMININO, TIPO CONJUNTO AUTO EXAME E AMAMENTAÇÃO, CARACTERÍSTICAS ADICIONAIS SEIO PANO BRANCO, SEIO NA PRANCHA MORENO",
    "Grupo": "69: APARELHOS E ACESSÓRIOS PARA TREINAMENTO",
    "Classe": "6910: ACESSÓRIOS PARA TREINAMENTO",
    "PDM": "09837: MODELO ANATÔMICO PARA FINS DIDÁTICOS",
    "Status": "Ativo",
    "Sustentável": "Não"
  },
  {
    "Código do Item": 395849,
    "Descrição do Item": "MODELO ANATÔMICO PARA FINS DIDÁTICOS , MATERIAL METAL, TAMANHO 17 X 17 X 22 CM, FINALIDADE MATERIAL EDUCATIVO ODONTOLÓGICO, TIPO MACRO ARCADA (SUPERIOR E INFERIOR) E ARTICULADOR, APLICAÇÃO TREINAMENTO, CARACTERÍSTICAS ADICIONAIS POSICIONA NA OCLUSÃO I/II/III E MORDIDA CRUZADA, OUTROS COMPONENTES MACRO ESCOVA TAMANHO 35X2,50 CM",
    "Grupo": "69: APARELHOS E ACESSÓRIOS PARA TREINAMENTO",
    "Classe": "6910: ACESSÓRIOS PARA TREINAMENTO",
    "PDM": "09837: MODELO ANATÔMICO PARA FINS DIDÁTICOS",
    "Status": "Ativo",
    "Sustentável": "Não"
  },
  {
    "Código do Item": 395850,
    "Descrição do Item": "MODELO ANATÔMICO PARA FINS DIDÁTICOS , MATERIAL ACRÍLICO, TAMANHO 6 X 19 CM, FINALIDADE MATERIAL EDUCATIVO ODONTOLÓGICO, TIPO EVOLUÇÃO DA CÁRIE DENTÁRIA, APLICAÇÃO TREINAMENTO, CARACTERÍSTICAS ADICIONAIS DEMONSTRAÇÃO FASES: DENTE SADIO/CÁRIE DENTINA/ENDO, OUTROS COMPONENTES MODELO COM 4 MACRO DENTES (ABRE E FECHA)",
    "Grupo": "69: APARELHOS E ACESSÓRIOS PARA TREINAMENTO",
    "Classe": "6910: ACESSÓRIOS PARA TREINAMENTO",
    "PDM": "09837: MODELO ANATÔMICO PARA FINS DIDÁTICOS",
    "Status": "Ativo",
    "Sustentável": "Não"
  },
  {
    "Código do Item": 395851,
    "Descrição do Item": "MODELO ANATÔMICO PARA FINS DIDÁTICOS , MATERIAL ACRÍLICO, TAMANHO 4,50 X 7 X 2,50 CM, FINALIDADE MATERIAL EDUCATIVO ODONTOLÓGICO, TIPO EVOLUÇÃO DA PERIODONTITE, APLICAÇÃO TREINAMENTO",
    "Grupo": "69: APARELHOS E ACESSÓRIOS PARA TREINAMENTO",
    "Classe": "6910: ACESSÓRIOS PARA TREINAMENTO",
    "PDM": "09837: MODELO ANATÔMICO PARA FINS DIDÁTICOS",
    "Status": "Ativo",
    "Sustentável": "Não"
  },
  {
    "Código do Item": 395858,
    "Descrição do Item": "MODELO ANATÔMICO PARA FINS DIDÁTICOS , MATERIAL ACRÍLICO, TAMANHO 20 X 18 X 10 CM, FINALIDADE MATERIAL EDUCATIVO ODONTOLÓGICO, TIPO MACRO MODELO MANDÍBULA TRANSPARENTE, APLICAÇÃO DEMONSTRAÇÃO DO RAMO MANDIBULAR DO TRIGÊMEO, CARACTERÍSTICAS ADICIONAIS DEMONSTRA DENTES DIFERENTES PATOLOGIAS/TRATAMENTOS",
    "Grupo": "69: APARELHOS E ACESSÓRIOS PARA TREINAMENTO",
    "Classe": "6910: ACESSÓRIOS PARA TREINAMENTO",
    "PDM": "09837: MODELO ANATÔMICO PARA FINS DIDÁTICOS",
    "Status": "Ativo",
    "Sustentável": "Não"
  },
  {
    "Código do Item": 403428,
    "Descrição do Item": "OBRÉIA , MATERIAL PAPEL CELULOSE VEGETAL, FORMATO CIRCULAR, APRESENTAÇÃO AUTO ADESIVA, COR AZUL CLARO, TAMANHO PADRÃO, APLICAÇÃO COBRIR FUROS CAUSADOS POR PROJÉTEIS NOS ALVOS.",
    "Grupo": "69: APARELHOS E ACESSÓRIOS PARA TREINAMENTO",
    "Classe": "6910: ACESSÓRIOS PARA TREINAMENTO",
    "PDM": "16111: OBRÉIA",
    "Status": "Ativo",
    "Sustentável": "Não"
  },
  {
    "Código do Item": 409658,
    "Descrição do Item": "MODELO ANATÔMICO PARA FINS DIDÁTICOS , ACESSÓRIOS BOLSA PARA TRANSPORTE, MATERIAL SILICONE, FINALIDADE RESSUSCITAÇÃO CARDIOPULMONAR, COM MANDÍBULA MÓVEL,, TIPO EXPANSAÃO TORÁXIA POR VENTILAÇÃO E MANDÍBULA MÓVEL, APLICAÇÃO TREINAMENTO, OUTROS COMPONENTES 2 FACE E 2 VIAS AÉREAS DESCARTÁVEL",
    "Grupo": "69: APARELHOS E ACESSÓRIOS PARA TREINAMENTO",
    "Classe": "6910: ACESSÓRIOS PARA TREINAMENTO",
    "PDM": "09837: MODELO ANATÔMICO PARA FINS DIDÁTICOS",
    "Status": "Ativo",
    "Sustentável": "Não"
  },
  {
    "Código do Item": 414172,
    "Descrição do Item": "PÊNDULO DE NEWTON , COMPONENTES HASTE E PÊNDULO, FINALIDADE ESTUDO DE OSCILAÇÕES HARMÔNICAS",
    "Grupo": "69: APARELHOS E ACESSÓRIOS PARA TREINAMENTO",
    "Classe": "6910: ACESSÓRIOS PARA TREINAMENTO",
    "PDM": "16586: PÊNDULO DE NEWTON",
    "Status": "Ativo",
    "Sustentável": "Não"
  },
  {
    "Código do Item": 419949,
    "Descrição do Item": "MODELO ANATÔMICO PARA FINS DIDÁTICOS , TAMANHO CERCA DE 8 X 8 X 10 CM, FINALIDADE MATERIAL EDUCATIVO ODONTOLÓGICO, TIPO MACRO ARCADA (SUPERIOR E INFERIOR) E ARTICULADOR, APLICAÇÃO TREINAMENTO HIGIENE DENTAL, CARACTERÍSTICAS ADICIONAIS POSIÇÃO: OCLUSÃO TIPO I, II, III E MORDIDA CRUZADA",
    "Grupo": "69: APARELHOS E ACESSÓRIOS PARA TREINAMENTO",
    "Classe": "6910: ACESSÓRIOS PARA TREINAMENTO",
    "PDM": "09837: MODELO ANATÔMICO PARA FINS DIDÁTICOS",
    "Status": "Ativo",
    "Sustentável": "Não"
  },
  {
    "Código do Item": 439253,
    "Descrição do Item": "KIT ELETRÔNICO , COMPONENTES TOMADA DE ENTRADA DE REDE C/3 PINOS,CHAVE LIGA/DES, REFERÊNCIA KIT PODCASTUDIO USB",
    "Grupo": "69: APARELHOS E ACESSÓRIOS PARA TREINAMENTO",
    "Classe": "6940: ACESSÓRIOS PARA TREINAMENTO DE COMUNICAÇÕES",
    "PDM": "08579: KIT ELETRÔNICO",
    "Status": "Inativo",
    "Sustentável": "Não"
  },
  {
    "Código do Item": 439254,
    "Descrição do Item": "KIT ELETRÔNICO , COMPONENTES ESTÚDIO COMPLETO DE GRAVAçãO PORTÁTIL DE ÁUDIO PRO, REFERÊNCIA KIT PODCASTUDIO USB",
    "Grupo": "69: APARELHOS E ACESSÓRIOS PARA TREINAMENTO",
    "Classe": "6940: ACESSÓRIOS PARA TREINAMENTO DE COMUNICAÇÕES",
    "PDM": "08579: KIT ELETRÔNICO",
    "Status": "Ativo",
    "Sustentável": "Não"
  },
  {
    "Código do Item": 440504,
    "Descrição do Item": "ACESSÓRIOS PARA ESTUDO/TREINAMENTO , TIPO COLEÇÃO DE ROCHAS ÍGNEAS, APRESENTAÇÃO LÂMINAS DELGADAS E POLIDAS, APLICAÇÃO ESTUDO DE MINERALOGIA",
    "Grupo": "69: APARELHOS E ACESSÓRIOS PARA TREINAMENTO",
    "Classe": "6910: ACESSÓRIOS PARA TREINAMENTO",
    "PDM": "17181: ACESSÓRIOS PARA ESTUDO/TREINAMENTO",
    "Status": "Ativo",
    "Sustentável": "Não"
  },
  {
    "Código do Item": 440505,
    "Descrição do Item": "ACESSÓRIOS PARA ESTUDO/TREINAMENTO , TIPO COLEÇÃO DE ROCHAS SEDIMENTARES, APRESENTAÇÃO LÂMINAS DELGADAS E POLIDAS, APLICAÇÃO ESTUDO DE MINERALOGIA",
    "Grupo": "69: APARELHOS E ACESSÓRIOS PARA TREINAMENTO",
    "Classe": "6910: ACESSÓRIOS PARA TREINAMENTO",
    "PDM": "17181: ACESSÓRIOS PARA ESTUDO/TREINAMENTO",
    "Status": "Ativo",
    "Sustentável": "Não"
  },
  {
    "Código do Item": 440506,
    "Descrição do Item": "ACESSÓRIOS PARA ESTUDO/TREINAMENTO , TIPO COLEÇÃO DE ROCHAS METAMÓRFICAS, APRESENTAÇÃO LÂMINAS DELGADAS E POLIDAS, APLICAÇÃO ESTUDO DE MINERALOGIA",
    "Grupo": "69: APARELHOS E ACESSÓRIOS PARA TREINAMENTO",
    "Classe": "6910: ACESSÓRIOS PARA TREINAMENTO",
    "PDM": "17181: ACESSÓRIOS PARA ESTUDO/TREINAMENTO",
    "Status": "Ativo",
    "Sustentável": "Não"
  },
  {
    "Código do Item": 440634,
    "Descrição do Item": "ACESSÓRIOS PARA ESTUDO/TREINAMENTO , TIPO CONJUNTO EDUCACIONAL MONTAGEM ROBÔS",
    "Grupo": "69: APARELHOS E ACESSÓRIOS PARA TREINAMENTO",
    "Classe": "6910: ACESSÓRIOS PARA TREINAMENTO",
    "PDM": "17181: ACESSÓRIOS PARA ESTUDO/TREINAMENTO",
    "Status": "Ativo",
    "Sustentável": "Não"
  },
  {
    "Código do Item": 440793,
    "Descrição do Item": "CONJUNTO INSTRUÇÃO , TIPO MATERIAL DIDÁTICO, COMPONENTES CRONÔMETRO, SENSORES E ESCALAS PARA ÂNGULO, FINALIDADE AULAS PRÁTICAS DE FíSICA, MECÂNICA DOS SÓLIDOS",
    "Grupo": "69: APARELHOS E ACESSÓRIOS PARA TREINAMENTO",
    "Classe": "6910: ACESSÓRIOS PARA TREINAMENTO",
    "PDM": "13720: CONJUNTO INSTRUÇÃO",
    "Status": "Ativo",
    "Sustentável": "Não"
  },
  {
    "Código do Item": 440872,
    "Descrição do Item": "CONJUNTO INSTRUÇÃO , TIPO MATERIAL DIDÁTICO, COMPONENTES DIAPASÕES/CONTRAPESO/CAIXAS DE RESSONÂNCIA/MARTELO, FINALIDADE AULAS PRÁTICAS DE FÍSICA, PROPAGAÇÃO DO SOM",
    "Grupo": "69: APARELHOS E ACESSÓRIOS PARA TREINAMENTO",
    "Classe": "6910: ACESSÓRIOS PARA TREINAMENTO",
    "PDM": "13720: CONJUNTO INSTRUÇÃO",
    "Status": "Ativo",
    "Sustentável": "Não"
  },
  {
    "Código do Item": 440873,
    "Descrição do Item": "CONJUNTO INSTRUÇÃO , TIPO MATERIAL DIDÁTICO, COMPONENTES PAINEL DE FORÇAS VERTICAL/TRIPÉ/SISTEMA MASSA/MOLA, FINALIDADE AULAS PRÁTICAS DE FÍSICA, MECÂNICA ESTÁTICA",
    "Grupo": "69: APARELHOS E ACESSÓRIOS PARA TREINAMENTO",
    "Classe": "6910: ACESSÓRIOS PARA TREINAMENTO",
    "PDM": "13720: CONJUNTO INSTRUÇÃO",
    "Status": "Ativo",
    "Sustentável": "Não"
  },
  {
    "Código do Item": 440874,
    "Descrição do Item": "CONJUNTO INSTRUÇÃO , TIPO MATERIAL DIDÁTICO, COMPONENTES BANCO ÓTICO/LENTES ESFÉRICAS/PRISMAS/ESPELHOS/FONT, FINALIDADE AULAS PRÁTICAS DE FÍSICA, ÓTICA",
    "Grupo": "69: APARELHOS E ACESSÓRIOS PARA TREINAMENTO",
    "Classe": "6910: ACESSÓRIOS PARA TREINAMENTO",
    "PDM": "13720: CONJUNTO INSTRUÇÃO",
    "Status": "Ativo",
    "Sustentável": "Não"
  },
  {
    "Código do Item": 440875,
    "Descrição do Item": "CONJUNTO INSTRUÇÃO , TIPO MATERIAL DIDÁTICO, COMPONENTES CORPOS DE PROVA E SUPORTES/CILINDRO/VENTOINHA COM, FINALIDADE AULAS PRÁTICAS DE FÍSICA, TERMODINÂMICA",
    "Grupo": "69: APARELHOS E ACESSÓRIOS PARA TREINAMENTO",
    "Classe": "6910: ACESSÓRIOS PARA TREINAMENTO",
    "PDM": "13720: CONJUNTO INSTRUÇÃO",
    "Status": "Ativo",
    "Sustentável": "Não"
  },
  {
    "Código do Item": 440876,
    "Descrição do Item": "CONJUNTO INSTRUÇÃO , TIPO MATERIAL DIDÁTICO, COMPONENTES PAINEL METÁLICO/TUBO \"U\"/VASOS/ESCALAS MILIMETRADA, FINALIDADE AULAS PRÁTICAS DE FÍSICA, MECÂNICA DOS FLUIDOS",
    "Grupo": "69: APARELHOS E ACESSÓRIOS PARA TREINAMENTO",
    "Classe": "6910: ACESSÓRIOS PARA TREINAMENTO",
    "PDM": "13720: CONJUNTO INSTRUÇÃO",
    "Status": "Ativo",
    "Sustentável": "Não"
  },
  {
    "Código do Item": 441366,
    "Descrição do Item": "CONJUNTO INSTRUÇÃO , TIPO MATERIAL DIDÁTICO, COMPONENTES CONVERSORES CC-CC/STEP-DOWN STEP UP/CONTROLE PWM/C, FINALIDADE AULAS PRÁTICAS ELETRÔNICA DE POTÊNCIA",
    "Grupo": "69: APARELHOS E ACESSÓRIOS PARA TREINAMENTO",
    "Classe": "6910: ACESSÓRIOS PARA TREINAMENTO",
    "PDM": "13720: CONJUNTO INSTRUÇÃO",
    "Status": "Ativo",
    "Sustentável": "Não"
  },
  {
    "Código do Item": 441422,
    "Descrição do Item": "CONJUNTO INSTRUÇÃO , TIPO MATERIAL DIDÁTICO, COMPONENTES CONVERSORES CC-CA/CHAVES SEMICONDUTORAS IGBT/CONVE, FINALIDADE AULAS PRÁTICAS ELETRÔNICA DE POTÊNCIA",
    "Grupo": "69: APARELHOS E ACESSÓRIOS PARA TREINAMENTO",
    "Classe": "6910: ACESSÓRIOS PARA TREINAMENTO",
    "PDM": "13720: CONJUNTO INSTRUÇÃO",
    "Status": "Ativo",
    "Sustentável": "Não"
  },
  {
    "Código do Item": 441424,
    "Descrição do Item": "CONJUNTO INSTRUÇÃO , TIPO MATERIAL DIDÁTICO, COMPONENTES MÁQUINA DE CARGA/TORQUÍMETRO E TACÔMETRO/MOTOR 1/2, FINALIDADE AULAS PRÁTICAS DO MOTOR TRIFÁSICO INDUÇÃO",
    "Grupo": "69: APARELHOS E ACESSÓRIOS PARA TREINAMENTO",
    "Classe": "6910: ACESSÓRIOS PARA TREINAMENTO",
    "PDM": "13720: CONJUNTO INSTRUÇÃO",
    "Status": "Ativo",
    "Sustentável": "Não"
  },
  {
    "Código do Item": 442376,
    "Descrição do Item": "ACESSÓRIOS PARA ESTUDO/TREINAMENTO , TIPO KIT V7 PARA ARDUINO COM BLACKBOARD V1.0, APRESENTAÇÃO COMPONENTES DA PLATAFORMA DE PROTOTIPAGEM ELETRÔNI, APLICAÇÃO USO DAS FUNCIONALIDADES DA PLACA ARDUINO",
    "Grupo": "69: APARELHOS E ACESSÓRIOS PARA TREINAMENTO",
    "Classe": "6910: ACESSÓRIOS PARA TREINAMENTO",
    "PDM": "17181: ACESSÓRIOS PARA ESTUDO/TREINAMENTO",
    "Status": "Ativo",
    "Sustentável": "Não"
  },
  {
    "Código do Item": 442410,
    "Descrição do Item": "ACESSÓRIOS PARA ESTUDO/TREINAMENTO , TIPO PLANO INCLINADO, APRESENTAÇÃO SENSORES E MULTICRONÔMETRO DE ROLAGEM DE DADOS, APLICAÇÃO ENSINO DA MECÂNICA DA PARTÍCULA/LEIS DE NEWTON/ MO",
    "Grupo": "69: APARELHOS E ACESSÓRIOS PARA TREINAMENTO",
    "Classe": "6910: ACESSÓRIOS PARA TREINAMENTO",
    "PDM": "17181: ACESSÓRIOS PARA ESTUDO/TREINAMENTO",
    "Status": "Ativo",
    "Sustentável": "Não"
  },
  {
    "Código do Item": 442419,
    "Descrição do Item": "ACESSÓRIOS PARA ESTUDO/TREINAMENTO , TIPO PLANO INCLINADO, APRESENTAÇÃO MÓDULO LEITOR RFID BASEADO NO CHIP MFRC522, APLICAÇÃO ESCRITA E LEITURA SEM CONTATO DE CARTÕES PARA CONT",
    "Grupo": "69: APARELHOS E ACESSÓRIOS PARA TREINAMENTO",
    "Classe": "6910: ACESSÓRIOS PARA TREINAMENTO",
    "PDM": "17181: ACESSÓRIOS PARA ESTUDO/TREINAMENTO",
    "Status": "Inativo",
    "Sustentável": "Não"
  },
  {
    "Código do Item": 442420,
    "Descrição do Item": "ACESSÓRIOS PARA ESTUDO/TREINAMENTO , TIPO KIT RFID, APRESENTAÇÃO MÓDULO LEITOR RFID BASEADO NO CHIP MFRC522, APLICAÇÃO ESCRITA E LEITURA SEM CONTATO DE CARTÕES PARA CONT",
    "Grupo": "69: APARELHOS E ACESSÓRIOS PARA TREINAMENTO",
    "Classe": "6910: ACESSÓRIOS PARA TREINAMENTO",
    "PDM": "17181: ACESSÓRIOS PARA ESTUDO/TREINAMENTO",
    "Status": "Ativo",
    "Sustentável": "Não"
  },
  {
    "Código do Item": 442542,
    "Descrição do Item": "KIT ELETRÔNICO , COMPONENTES 65 JAMPER DE COBRE BITOLA 22\" (49 DE 110MM, 8 DE, TIPO JUMPERS MACHO-MACHO PARA PROJETOS ELETRôNICOS COM",
    "Grupo": "69: APARELHOS E ACESSÓRIOS PARA TREINAMENTO",
    "Classe": "6940: ACESSÓRIOS PARA TREINAMENTO DE COMUNICAÇÕES",
    "PDM": "08579: KIT ELETRÔNICO",
    "Status": "Ativo",
    "Sustentável": "Não"
  },
  {
    "Código do Item": 442543,
    "Descrição do Item": "KIT ELETRÔNICO , COMPONENTES 40 JAMPER DE COBRE, COR MULTICOLORIDO, BITOLA 24\", TIPO JUMPERS MACHO-FEMEA PARA PROJETOS ELETRôNICOS COM",
    "Grupo": "69: APARELHOS E ACESSÓRIOS PARA TREINAMENTO",
    "Classe": "6940: ACESSÓRIOS PARA TREINAMENTO DE COMUNICAÇÕES",
    "PDM": "08579: KIT ELETRÔNICO",
    "Status": "Ativo",
    "Sustentável": "Não"
  },
  {
    "Código do Item": 442544,
    "Descrição do Item": "KIT ELETRÔNICO , COMPONENTES 40 JAMPER DE COBRE, COR MULTICOLORIDO, BITOLA 24\", TIPO JUMPERS FEMEA-FEMEA PARA PROJETOS ELETRôNICOS COM",
    "Grupo": "69: APARELHOS E ACESSÓRIOS PARA TREINAMENTO",
    "Classe": "6940: ACESSÓRIOS PARA TREINAMENTO DE COMUNICAÇÕES",
    "PDM": "08579: KIT ELETRÔNICO",
    "Status": "Ativo",
    "Sustentável": "Não"
  },
  {
    "Código do Item": 442686,
    "Descrição do Item": "ACESSÓRIOS PARA ESTUDO/TREINAMENTO , TIPO CONJUNTO PARA UTILIZAÇÃO CONVENCIONAL OU MONITORA, APRESENTAÇÃO UNIDADE MESTRA DE FÍSICA COM HIDRODINÂMICA, SENSOR, APLICAÇÃO ESTUDO DA MECÂNICA DOS SÓLIDOS E FLUIDOS, ÓPTICA,",
    "Grupo": "69: APARELHOS E ACESSÓRIOS PARA TREINAMENTO",
    "Classe": "6910: ACESSÓRIOS PARA TREINAMENTO",
    "PDM": "17181: ACESSÓRIOS PARA ESTUDO/TREINAMENTO",
    "Status": "Ativo",
    "Sustentável": "Não"
  },
  {
    "Código do Item": 443025,
    "Descrição do Item": "ACESSÓRIOS PARA ESTUDO/TREINAMENTO , TIPO AMOSTRA PADRÃO DE CIMENTO, APRESENTAÇÃO FRASCO COM 18 GRAMAS COM CERTIFICAÇÃO, APLICAÇÃO CALIBRAÇÃO DO PERMEABILÍMETRO DE BLAINE",
    "Grupo": "69: APARELHOS E ACESSÓRIOS PARA TREINAMENTO",
    "Classe": "6910: ACESSÓRIOS PARA TREINAMENTO",
    "PDM": "17181: ACESSÓRIOS PARA ESTUDO/TREINAMENTO",
    "Status": "Ativo",
    "Sustentável": "Não"
  },
  {
    "Código do Item": 443330,
    "Descrição do Item": "ACESSÓRIOS PARA ESTUDO/TREINAMENTO , TIPO KIT PROTOTIPAGEM, APRESENTAÇÃO CABO FLAT: 40 VIAS FÊMEA/FÊMEA, ADAPTADOR PARA PRO, APLICAÇÃO RASPBERRY PI3, PI2 E B+",
    "Grupo": "69: APARELHOS E ACESSÓRIOS PARA TREINAMENTO",
    "Classe": "6910: ACESSÓRIOS PARA TREINAMENTO",
    "PDM": "17181: ACESSÓRIOS PARA ESTUDO/TREINAMENTO",
    "Status": "Ativo",
    "Sustentável": "Não"
  },
  {
    "Código do Item": 443712,
    "Descrição do Item": "ALVO DE TIRO , MATERIAL PAPELÃO KRAFT, TIPO RETANGULAR, TAMANHO 90 X 60 CM",
    "Grupo": "69: APARELHOS E ACESSÓRIOS PARA TREINAMENTO",
    "Classe": "6920: ACESSÓRIOS PARA TREINAMENTO DE ARMAMENTO",
    "PDM": "02382: ALVO DE TIRO",
    "Status": "Ativo",
    "Sustentável": "Não"
  },
  {
    "Código do Item": 444852,
    "Descrição do Item": "ALVO DE TIRO , MATERIAL PAPEL KRAFT 90GG, TIPO RETANGULAR, TAMANHO 100X50 CM, CARACTERÍSTICAS ADICIONAIS ALVO PARA FUZIL",
    "Grupo": "69: APARELHOS E ACESSÓRIOS PARA TREINAMENTO",
    "Classe": "6920: ACESSÓRIOS PARA TREINAMENTO DE ARMAMENTO",
    "PDM": "02382: ALVO DE TIRO",
    "Status": "Inativo",
    "Sustentável": "Não"
  },
  {
    "Código do Item": 444854,
    "Descrição do Item": "ALVO DE TIRO , MATERIAL PAPEL KRAFT, TIPO RETANGULAR, TAMANHO 100X50 CM, CARACTERÍSTICAS ADICIONAIS ALVO PARA FUZIL, GRAMATURA 90 G/M2",
    "Grupo": "69: APARELHOS E ACESSÓRIOS PARA TREINAMENTO",
    "Classe": "6920: ACESSÓRIOS PARA TREINAMENTO DE ARMAMENTO",
    "PDM": "02382: ALVO DE TIRO",
    "Status": "Ativo",
    "Sustentável": "Não"
  },
  {
    "Código do Item": 444938,
    "Descrição do Item": "CONJUNTO INSTRUÇÃO , TIPO MATERIAL DIDÁTICO, COMPONENTES, FINALIDADE",
    "Grupo": "69: APARELHOS E ACESSÓRIOS PARA TREINAMENTO",
    "Classe": "6910: ACESSÓRIOS PARA TREINAMENTO",
    "PDM": "13720: CONJUNTO INSTRUÇÃO",
    "Status": "Ativo",
    "Sustentável": "Não"
  },
  {
    "Código do Item": 445114,
    "Descrição do Item": "ALVO DE TIRO , MATERIAL PAPEL CARTÃO, TIPO QUADRADO, TAMANHO 20 X 20 CM, CARACTERÍSTICAS ADICIONAIS SILHUETA PRETA",
    "Grupo": "69: APARELHOS E ACESSÓRIOS PARA TREINAMENTO",
    "Classe": "6920: ACESSÓRIOS PARA TREINAMENTO DE ARMAMENTO",
    "PDM": "02382: ALVO DE TIRO",
    "Status": "Ativo",
    "Sustentável": "Não"
  },
  {
    "Código do Item": 445115,
    "Descrição do Item": "ALVO DE TIRO , MATERIAL PAPEL CARTÃO, TIPO RETANGULAR, TAMANHO CM, CARACTERÍSTICAS ADICIONAIS SILHUETA PRETA",
    "Grupo": "69: APARELHOS E ACESSÓRIOS PARA TREINAMENTO",
    "Classe": "6920: ACESSÓRIOS PARA TREINAMENTO DE ARMAMENTO",
    "PDM": "02382: ALVO DE TIRO",
    "Status": "Ativo",
    "Sustentável": "Não"
  },
  {
    "Código do Item": 445222,
    "Descrição do Item": "ACESSÓRIOS PARA ESTUDO/TREINAMENTO , TIPO, APRESENTAÇÃO, APLICAÇÃO",
    "Grupo": "69: APARELHOS E ACESSÓRIOS PARA TREINAMENTO",
    "Classe": "6910: ACESSÓRIOS PARA TREINAMENTO",
    "PDM": "17181: ACESSÓRIOS PARA ESTUDO/TREINAMENTO",
    "Status": "Ativo",
    "Sustentável": "Não"
  },
  {
    "Código do Item": 445223,
    "Descrição do Item": "ACESSÓRIOS PARA ESTUDO/TREINAMENTO , TIPO, APRESENTAÇÃO, APLICAÇÃO",
    "Grupo": "69: APARELHOS E ACESSÓRIOS PARA TREINAMENTO",
    "Classe": "6910: ACESSÓRIOS PARA TREINAMENTO",
    "PDM": "17181: ACESSÓRIOS PARA ESTUDO/TREINAMENTO",
    "Status": "Ativo",
    "Sustentável": "Não"
  }
]
