[
  {
    "id": "09787",
    "pdm": "MISSIL TELEGUIADO"
  },
  {
    "id": 16725,
    "pdm": "MÍSSEIS GUIADOS"
  },
  {
    "id": 16726,
    "pdm": "COMPONENTES DE MÍSSEIS GUIADOS"
  },
  {
    "id": 16727,
    "pdm": "SISTEMAS COMPLETOS DE MÍSSEIS GUIADOS"
  },
  {
    "id": 16728,
    "pdm": "SUBSISTEMAS DE MÍSSEIS GUIADOS"
  },
  {
    "id": 16729,
    "pdm": "SISTEMA DE CONTROLE REMOTO DE MÍSSEIS GUIADOS"
  },
  {
    "id": 16730,
    "pdm": "LANÇADORES DE MÍSSEIS GUIADOS"
  },
  {
    "id": 16731,
    "pdm": "EQUIPAMENTO PARA MANUSEIO DE MANUTENÇÃO DE MÍSSEIS GUIADOS"
  },
  {
    "id": 16732,
    "pdm": "MISSEIS GUIADOS DIVERSOS"
  }
]